{
  "strategy": "both",
  "symbol": "ETHUSD",
  "start_date": "2025-06-02 01:00:00+00:00",
  "end_date": "2026-03-01 00:00:00+00:00",
  "initial_capital": 30.0,
  "final_equity": 138.7037621620829,
  "total_return_pct": 362.3458738736097,
  "max_drawdown_pct": 17.0440098224875,
  "win_rate": 61.940298507462686,
  "profit_factor": 2.119535075311043,
  "total_trades": 134,
  "avg_trade_pnl": 0.8112221056871857,
  "sharpe_ratio": 0.3597962198778854,
  "sortino_ratio": 0.3788428189033515,
  "max_consecutive_losses": 5,
  "max_consecutive_wins": 12,
  "avg_trade_duration_hours": 24.595149253731343,
  "best_trade_pnl": 17.796999999999777,
  "worst_trade_pnl": -4.038300000000031,
  "expectancy": 0.8112221056871858,
  "trades": [
    {
      "ticket": 1,
      "side": "BUY",
      "open_price": 2631.27,
      "close_price": 2603.630330024171,
      "open_time": "2025-06-03 17:15:00+00:00",
      "close_time": "2025-06-03 19:45:00+00:00",
      "pnl": -0.8291900992748651,
      "close_reason": "STOP_LOSS"
    },
    {
      "ticket": 2,
      "side": "BUY",
      "open_price": 2639.48,
      "close_price": 2575.81,
      "open_time": "2025-06-04 11:45:00+00:00",
      "close_time": "2025-06-05 17:15:00+00:00",
      "pnl": -0.6367000000000007,
      "close_reason": "STOP_LOSS"
    },
    {
      "ticket": 3,
      "side": "BUY",
      "open_price": 2457.43,
      "close_price": 2524.32196,
      "open_time": "2025-06-06 07:45:00+00:00",
      "close_time": "2025-06-08 02:15:00+00:00",
      "pnl": 0.6689196000000038,
      "close_reason": "STOP_LOSS"
    },
    {
      "ticket": 4,
      "side": "SELL",
      "open_price": 2479.32,
      "close_price": 2547.38,
      "open_time": "2025-06-09 08:45:00+00:00",
      "close_time": "2025-06-09 19:15:00+00:00",
      "pnl": -0.6805999999999994,
      "close_reason": "STOP_LOSS"
    },
    {
      "ticket": 5,
      "side": "BUY",
      "open_price": 2815.48,
      "close_price": 2835.10567,
      "open_time": "2025-06-11 16:15:00+00:00",
      "close_time": "2025-06-11 20:00:00+00:00",
      "pnl": 0.392513399999998,
      "close_reason": "STOP_LOSS"
    },
    {
      "ticket": 6,
      "side": "SELL",
      "open_price": 2739.52,
      "close_price": 2495.94257,
      "open_time": "2025-06-12 10:45:00+00:00",
      "close_time": "2025-06-13 06:00:00+00:00",
      "pnl": 2.435774299999998,
      "close_reason": "STOP_LOSS"
    },
    {
      "ticket": 7,
      "side": "SELL",
      "open_price": 2536.08,
      "close_price": 2510.52995,
      "open_time": "2025-06-14 10:00:00+00:00",
      "close_time": "2025-06-14 20:15:00+00:00",
      "pnl": 0.5110009999999966,
      "close_reason": "STOP_LOSS"
    },
    {
      "ticket": 8,
      "side": "BUY",
      "open_price": 2542.09,
      "close_price": 2504.89,
      "open_time": "2025-06-15 07:45:00+00:00",
      "close_time": "2025-06-15 23:30:00+00:00",
      "pnl": -1.116000000000008,
      "close_reason": "STOP_LOSS"
    },
    {
      "ticket": 9,
      "side": "BUY",
      "open_price": 2595.8,
      "close_price": 2496.17,
      "open_time": "2025-06-16 08:15:00+00:00",
      "close_time": "2025-06-17 18:15:00+00:00",
      "pnl": -0.9963000000000011,
      "close_reason": "STOP_LOSS"
    },
    {
      "ticket": 10,
      "side": "BUY",
      "open_price": 2536.56,
      "close_price": 2490.47,
      "open_time": "2025-06-18 08:15:00+00:00",
      "close_time": "2025-06-18 13:45:00+00:00",
      "pnl": -0.921800000000003,
      "close_reason": "STOP_LOSS"
    },
    {
      "ticket": 11,
      "side": "BUY",
      "open_price": 2564.1,
      "close_price": 2502.99,
      "open_time": "2025-06-20 11:00:00+00:00",
      "close_time": "2025-06-20 17:45:00+00:00",
      "pnl": -0.6111000000000013,
      "close_reason": "STOP_LOSS"
    },
    {
      "ticket": 12,
      "side": "BUY",
      "open_price": 2440.27,
      "close_price": 2381.01,
      "open_time": "2025-06-21 11:45:00+00:00",
      "close_time": "2025-06-21 23:00:00+00:00",
      "pnl": -0.5925999999999977,
      "close_reason": "STOP_LOSS"
    },
    {
      "ticket": 13,
      "side": "BUY",
      "open_price": 2260.28,
      "close_price": 2385.75082,
      "open_time": "2025-06-23 10:00:00+00:00",
      "close_time": "2025-06-24 01:30:00+00:00",
      "pnl": 1.2547082,
      "close_reason": "STOP_LOSS"
    },
    {
      "ticket": 14,
      "side": "BUY",
      "open_price": 2456.99,
      "close_price": 2428.328676595806,
      "open_time": "2025-06-25 03:45:00+00:00",
      "close_time": "2025-06-25 07:45:00+00:00",
      "pnl": -0.8598397021258142,
      "close_reason": "STOP_LOSS"
    },
    {
      "ticket": 15,
      "side": "SELL",
      "open_price": 2428.99,
      "close_price": 2467.17,
      "open_time": "2025-06-25 11:30:00+00:00",
      "close_time": "2025-06-26 04:30:00+00:00",
      "pnl": -0.7636000000000058,
      "close_reason": "STOP_LOSS"
    },
    {
      "ticket": 16,
      "side": "BUY",
      "open_price": 2447.44,
      "close_price": 2498.08969,
      "open_time": "2025-06-27 07:15:00+00:00",
      "close_time": "2025-06-30 06:15:00+00:00",
      "pnl": 0.5064968999999974,
      "close_reason": "STOP_LOSS"
    },
    {
      "ticket": 17,
      "side": "SELL",
      "open_price": 2459.59,
      "close_price": 2444.26521,
      "open_time": "2025-07-01 07:45:00+00:00",
      "close_time": "2025-07-01 17:00:00+00:00",
      "pnl": 0.3064958000000024,
      "close_reason": "STOP_LOSS"
    },
    {
      "ticket": 18,
      "side": "BUY",
      "open_price": 2434.06,
      "close_price": 2556.66955,
      "open_time": "2025-07-02 07:30:00+00:00",
      "close_time": "2025-07-02 20:30:00+00:00",
      "pnl": 1.2260955000000013,
      "close_reason": "STOP_LOSS"
    },
    {
      "ticket": 19,
      "side": "SELL",
      "open_price": 2568.85,
      "close_price": 2542.52969,
      "open_time": "2025-07-04 07:45:00+00:00",
      "close_time": "2025-07-04 11:15:00+00:00",
      "pnl": 0.7896093000000018,
      "close_reason": "STOP_LOSS"
    },
    {
      "ticket": 20,
      "side": "BUY",
      "open_price": 2523.6,
      "close_price": 2581.77232,
      "open_time": "2025-07-05 07:15:00+00:00",
      "close_time": "2025-07-07 01:45:00+00:00",
      "pnl": 1.1634464000000027,
      "close_reason": "STOP_LOSS"
    },
    {
      "ticket": 21,
      "side": "BUY",
      "open_price": 2558.57,
      "close_price": 2603.30678,
      "open_time": "2025-07-08 11:00:00+00:00",
      "close_time": "2025-07-08 22:30:00+00:00",
      "pnl": 1.3421033999999916,
      "close_reason": "STOP_LOSS"
    },
    {
      "ticket": 22,
      "side": "BUY",
      "open_price": 2634.66,
      "close_price": 2738.66054,
      "open_time": "2025-07-09 08:30:00+00:00",
      "close_time": "2025-07-09 23:15:00+00:00",
      "pnl": 2.0800108,
      "close_reason": "STOP_LOSS"
    },
    {
      "ticket": 23,
      "side": "BUY",
      "open_price": 2816.01,
      "close_price": 2933.66134,
      "open_time": "2025-07-10 10:00:00+00:00",
      "close_time": "2025-07-11 03:15:00+00:00",
      "pnl": 1.176513399999999,
      "close_reason": "STOP_LOSS"
    },
    {
      "ticket": 24,
      "side": "BUY",
      "open_price": 3009.27,
      "close_price": 3222.27108,
      "open_time": "2025-07-11 08:30:00+00:00",
      "close_time": "2025-07-16 18:15:00+00:00",
      "pnl": 2.1300108,
      "close_reason": "STOP_LOSS"
    },
    {
      "ticket": 25,
      "side": "BUY",
      "open_price": 3423.23,
      "close_price": 3630.90628,
      "open_time": "2025-07-17 09:15:00+00:00",
      "close_time": "2025-07-18 10:00:00+00:00",
      "pnl": 2.0767628000000014,
      "close_reason": "STOP_LOSS"
    },
    {
      "ticket": 26,
      "side": "BUY",
      "open_price": 3638.65,
      "close_price": 3835.41459,
      "open_time": "2025-07-18 10:00:00+00:00",
      "close_time": "2025-07-27 22:15:00+00:00",
      "pnl": 1.9676458999999977,
      "close_reason": "STOP_LOSS"
    },
    {
      "ticket": 27,
      "side": "BUY",
      "open_price": 3872.76,
      "close_price": 3911.64856,
      "open_time": "2025-07-28 01:30:00+00:00",
      "close_time": "2025-07-28 09:30:00+00:00",
      "pnl": 1.1666567999999962,
      "close_reason": "STOP_LOSS"
    },
    {
      "ticket": 28,
      "side": "BUY",
      "open_price": 3910.8,
      "close_price": 3814.7,
      "open_time": "2025-07-28 09:30:00+00:00",
      "close_time": "2025-07-28 17:15:00+00:00",
      "pnl": -0.9610000000000036,
      "close_reason": "STOP_LOSS"
    },
    {
      "ticket": 29,
      "side": "BUY",
      "open_price": 3827.85,
      "close_price": 3752.41,
      "open_time": "2025-07-30 10:15:00+00:00",
      "close_time": "2025-07-30 14:30:00+00:00",
      "pnl": -1.508800000000001,
      "close_reason": "STOP_LOSS"
    },
    {
      "ticket": 30,
      "side": "BUY",
      "open_price": 3869.66,
      "close_price": 3741.13,
      "open_time": "2025-07-31 07:45:00+00:00",
      "close_time": "2025-07-31 22:45:00+00:00",
      "pnl": -1.2852999999999974,
      "close_reason": "STOP_LOSS"
    },
    {
      "ticket": 31,
      "side": "SELL",
      "open_price": 3612.32,
      "close_price": 3504.20493,
      "open_time": "2025-08-01 11:00:00+00:00",
      "close_time": "2025-08-02 03:45:00+00:00",
      "pnl": 1.081150700000003,
      "close_reason": "STOP_LOSS"
    },
    {
      "ticket": 32,
      "side": "BUY",
      "open_price": 3451.16,
      "close_price": 3545.18032,
      "open_time": "2025-08-03 08:15:00+00:00",
      "close_time": "2025-08-04 07:30:00+00:00",
      "pnl": 0.9402032000000009,
      "close_reason": "STOP_LOSS"
    },
    {
      "ticket": 33,
      "side": "BUY",
      "open_price": 3546.74,
      "close_price": 3628.77317,
      "open_time": "2025-08-04 10:30:00+00:00",
      "close_time": "2025-08-04 17:45:00+00:00",
      "pnl": 3.281326800000006,
      "close_reason": "STOP_LOSS"
    },
    {
      "ticket": 34,
      "side": "SELL",
      "open_price": 3646.49,
      "close_price": 3735.54,
      "open_time": "2025-08-05 07:30:00+00:00",
      "close_time": "2025-08-07 13:00:00+00:00",
      "pnl": -1.7810000000000037,
      "close_reason": "STOP_LOSS"
    },
    {
      "ticket": 35,
      "side": "BUY",
      "open_price": 4033.54,
      "close_price": 4159.2863243447155,
      "open_time": "2025-08-09 05:30:00+00:00",
      "close_time": "2025-08-09 08:00:00+00:00",
      "pnl": 5.02985297378862,
      "close_reason": "TAKE_PROFIT"
    },
    {
      "ticket": 36,
      "side": "BUY",
      "open_price": 4157.91,
      "close_price": 4196.09922,
      "open_time": "2025-08-09 08:00:00+00:00",
      "close_time": "2025-08-09 14:30:00+00:00",
      "pnl": 0.38189220000000207,
      "close_reason": "STOP_LOSS"
    },
    {
      "ticket": 37,
      "side": "BUY",
      "open_price": 4311.64,
      "close_price": 4573.94052,
      "open_time": "2025-08-12 10:15:00+00:00",
      "close_time": "2025-08-13 01:00:00+00:00",
      "pnl": 2.623005199999998,
      "close_reason": "STOP_LOSS"
    },
    {
      "ticket": 38,
      "side": "BUY",
      "open_price": 4663.42,
      "close_price": 4719.38917,
      "open_time": "2025-08-13 07:00:00+00:00",
      "close_time": "2025-08-14 03:30:00+00:00",
      "pnl": 1.119383400000006,
      "close_reason": "STOP_LOSS"
    },
    {
      "ticket": 39,
      "side": "BUY",
      "open_price": 4658.82,
      "close_price": 4452.14,
      "open_time": "2025-08-15 09:30:00+00:00",
      "close_time": "2025-08-15 18:15:00+00:00",
      "pnl": -2.066799999999994,
      "close_reason": "STOP_LOSS"
    },
    {
      "ticket": 40,
      "side": "BUY",
      "open_price": 4471.19,
      "close_price": 4540.132,
      "open_time": "2025-08-17 07:15:00+00:00",
      "close_time": "2025-08-17 15:00:00+00:00",
      "pnl": 1.37884,
      "close_reason": "STOP_LOSS"
    },
    {
      "ticket": 41,
      "side": "SELL",
      "open_price": 4447.38,
      "close_price": 4234.3742950193455,
      "open_time": "2025-08-18 03:15:00+00:00",
      "close_time": "2025-08-18 09:45:00+00:00",
      "pnl": 6.390171149419639,
      "close_reason": "TAKE_PROFIT"
    },
    {
      "ticket": 42,
      "side": "SELL",
      "open_price": 4251.37,
      "close_price": 4533.19,
      "open_time": "2025-08-18 09:45:00+00:00",
      "close_time": "2025-08-22 17:00:00+00:00",
      "pnl": -2.818199999999997,
      "close_reason": "STOP_LOSS"
    },
    {
      "ticket": 43,
      "side": "BUY",
      "open_price": 4791.93,
      "close_price": 4750.21521334782,
      "open_time": "2025-08-24 07:45:00+00:00",
      "close_time": "2025-08-24 11:00:00+00:00",
      "pnl": -1.6685914660872003,
      "close_reason": "STOP_LOSS"
    },
    {
      "ticket": 44,
      "side": "SELL",
      "open_price": 4651.88,
      "close_price": 4406.22316,
      "open_time": "2025-08-25 09:30:00+00:00",
      "close_time": "2025-08-26 01:30:00+00:00",
      "pnl": 2.4565684000000054,
      "close_reason": "STOP_LOSS"
    },
    {
      "ticket": 45,
      "side": "BUY",
      "open_price": 4636.0,
      "close_price": 4538.79,
      "open_time": "2025-08-27 08:00:00+00:00",
      "close_time": "2025-08-27 22:00:00+00:00",
      "pnl": -1.9442000000000008,
      "close_reason": "STOP_LOSS"
    },
    {
      "ticket": 46,
      "side": "BUY",
      "open_price": 4617.82,
      "close_price": 4465.93,
      "open_time": "2025-08-28 11:00:00+00:00",
      "close_time": "2025-08-28 19:45:00+00:00",
      "pnl": -1.5188999999999941,
      "close_reason": "STOP_LOSS"
    },
    {
      "ticket": 47,
      "side": "SELL",
      "open_price": 4463.85,
      "close_price": 4359.78742,
      "open_time": "2025-08-29 09:00:00+00:00",
      "close_time": "2025-08-29 13:15:00+00:00",
      "pnl": 4.162503200000028,
      "close_reason": "STOP_LOSS"
    },
    {
      "ticket": 48,
      "side": "BUY",
      "open_price": 4485.41,
      "close_price": 4445.535542918496,
      "open_time": "2025-08-31 18:30:00+00:00",
      "close_time": "2025-08-31 23:00:00+00:00",
      "pnl": -1.5949782832601704,
      "close_reason": "STOP_LOSS"
    },
    {
      "ticket": 49,
      "side": "SELL",
      "open_price": 4375.57,
      "close_price": 4305.96669,
      "open_time": "2025-09-04 09:00:00+00:00",
      "close_time": "2025-09-04 23:15:00+00:00",
      "pnl": 1.3920661999999902,
      "close_reason": "STOP_LOSS"
    },
    {
      "ticket": 50,
      "side": "BUY",
      "open_price": 4397.76,
      "close_price": 4435.11181,
      "open_time": "2025-09-05 11:00:00+00:00",
      "close_time": "2025-09-05 16:45:00+00:00",
      "pnl": 0.7470362000000023,
      "close_reason": "STOP_LOSS"
    },
    {
      "ticket": 51,
      "side": "BUY",
      "open_price": 4307.5,
      "close_price": 4335.80036,
      "open_time": "2025-09-07 11:15:00+00:00",
      "close_time": "2025-09-08 16:15:00+00:00",
      "pnl": 1.1320144000000074,
      "close_reason": "STOP_LOSS"
    },
    {
      "ticket": 52,
      "side": "BUY",
      "open_price": 4340.96,
      "close_price": 4404.26981,
      "open_time": "2025-09-09 09:00:00+00:00",
      "close_time": "2025-09-10 17:45:00+00:00",
      "pnl": 1.8992942999999922,
      "close_reason": "STOP_LOSS"
    },
    {
      "ticket": 53,
      "side": "BUY",
      "open_price": 4411.89,
      "close_price": 4504.81884,
      "open_time": "2025-09-11 07:15:00+00:00",
      "close_time": "2025-09-12 04:45:00+00:00",
      "pnl": 1.8585767999999916,
      "close_reason": "STOP_LOSS"
    },
    {
      "ticket": 54,
      "side": "BUY",
      "open_price": 4556.38,
      "close_price": 4680.35233,
      "open_time": "2025-09-12 08:45:00+00:00",
      "close_time": "2025-09-13 02:00:00+00:00",
      "pnl": 1.239723299999996,
      "close_reason": "STOP_LOSS"
    },
    {
      "ticket": 55,
      "side": "BUY",
      "open_price": 4648.64,
      "close_price": 4578.9,
      "open_time": "2025-09-15 08:00:00+00:00",
      "close_time": "2025-09-15 11:00:00+00:00",
      "pnl": -2.0922000000000205,
      "close_reason": "STOP_LOSS"
    },
    {
      "ticket": 56,
      "side": "SELL",
      "open_price": 4503.03,
      "close_price": 4458.40296,
      "open_time": "2025-09-16 11:30:00+00:00",
      "close_time": "2025-09-16 18:45:00+00:00",
      "pnl": 2.23135199999997,
      "close_reason": "STOP_LOSS"
    },
    {
      "ticket": 57,
      "side": "SELL",
      "open_price": 4475.82,
      "close_price": 4551.6,
      "open_time": "2025-09-17 07:45:00+00:00",
      "close_time": "2025-09-17 10:15:00+00:00",
      "pnl": -2.2734000000000196,
      "close_reason": "STOP_LOSS"
    },
    {
      "ticket": 58,
      "side": "BUY",
      "open_price": 4615.3,
      "close_price": 4585.11640558857,
      "open_time": "2025-09-19 04:15:00+00:00",
      "close_time": "2025-09-19 06:15:00+00:00",
      "pnl": -1.8110156646858013,
      "close_reason": "STOP_LOSS"
    },
    {
      "ticket": 59,
      "side": "SELL",
      "open_price": 4532.23,
      "close_price": 4464.42976,
      "open_time": "2025-09-19 09:00:00+00:00",
      "close_time": "2025-09-20 00:30:00+00:00",
      "pnl": 1.3560047999999916,
      "close_reason": "STOP_LOSS"
    },
    {
      "ticket": 60,
      "side": "BUY",
      "open_price": 4477.38,
      "close_price": 4445.2,
      "open_time": "2025-09-20 08:45:00+00:00",
      "close_time": "2025-09-21 12:30:00+00:00",
      "pnl": -1.9308000000000174,
      "close_reason": "STOP_LOSS"
    },
    {
      "ticket": 61,
      "side": "SELL",
      "open_price": 4219.14,
      "close_price": 4041.04064,
      "open_time": "2025-09-22 08:45:00+00:00",
      "close_time": "2025-09-25 12:15:00+00:00",
      "pnl": 1.7809936000000017,
      "close_reason": "STOP_LOSS"
    },
    {
      "ticket": 62,
      "side": "SELL",
      "open_price": 3908.36,
      "close_price": 3958.3666665450933,
      "open_time": "2025-09-26 10:30:00+00:00",
      "close_time": "2025-09-26 15:30:00+00:00",
      "pnl": -2.0002666618037255,
      "close_reason": "STOP_LOSS"
    },
    {
      "ticket": 63,
      "side": "SELL",
      "open_price": 4169.21,
      "close_price": 4124.61287,
      "open_time": "2025-09-30 11:30:00+00:00",
      "close_time": "2025-09-30 22:15:00+00:00",
      "pnl": 0.8919426000000021,
      "close_reason": "STOP_LOSS"
    },
    {
      "ticket": 64,
      "side": "BUY",
      "open_price": 4270.01,
      "close_price": 4353.57136,
      "open_time": "2025-10-01 11:30:00+00:00",
      "close_time": "2025-10-02 03:15:00+00:00",
      "pnl": 0.835613599999997,
      "close_reason": "STOP_LOSS"
    },
    {
      "ticket": 65,
      "side": "BUY",
      "open_price": 4400.46,
      "close_price": 4474.83142,
      "open_time": "2025-10-02 09:15:00+00:00",
      "close_time": "2025-10-02 23:30:00+00:00",
      "pnl": 1.487428400000008,
      "close_reason": "STOP_LOSS"
    },
    {
      "ticket": 66,
      "side": "BUY",
      "open_price": 4491.82,
      "close_price": 4503.4544,
      "open_time": "2025-10-03 05:00:00+00:00",
      "close_time": "2025-10-03 06:45:00+00:00",
      "pnl": 0.5817199999999957,
      "close_reason": "STOP_LOSS"
    },
    {
      "ticket": 67,
      "side": "SELL",
      "open_price": 4452.41,
      "close_price": 4558.38,
      "open_time": "2025-10-03 10:15:00+00:00",
      "close_time": "2025-10-03 19:30:00+00:00",
      "pnl": -2.119400000000005,
      "close_reason": "STOP_LOSS"
    },
    {
      "ticket": 68,
      "side": "BUY",
      "open_price": 4575.92,
      "close_price": 4687.45193,
      "open_time": "2025-10-05 08:15:00+00:00",
      "close_time": "2025-10-06 23:30:00+00:00",
      "pnl": 2.230638600000002,
      "close_reason": "STOP_LOSS"
    },
    {
      "ticket": 69,
      "side": "BUY",
      "open_price": 4690.35,
      "close_price": 4700.84147,
      "open_time": "2025-10-07 07:15:00+00:00",
      "close_time": "2025-10-07 09:00:00+00:00",
      "pnl": 0.5245734999999968,
      "close_reason": "STOP_LOSS"
    },
    {
      "ticket": 70,
      "side": "SELL",
      "open_price": 4651.42,
      "close_price": 4705.82,
      "open_time": "2025-10-07 11:00:00+00:00",
      "close_time": "2025-10-07 14:30:00+00:00",
      "pnl": -1.631999999999989,
      "close_reason": "STOP_LOSS"
    },
    {
      "ticket": 71,
      "side": "SELL",
      "open_price": 4428.53,
      "close_price": 4513.15,
      "open_time": "2025-10-08 08:30:00+00:00",
      "close_time": "2025-10-08 17:00:00+00:00",
      "pnl": -1.692399999999998,
      "close_reason": "STOP_LOSS"
    },
    {
      "ticket": 72,
      "side": "SELL",
      "open_price": 4338.19,
      "close_price": 4013.02186,
      "open_time": "2025-10-09 11:15:00+00:00",
      "close_time": "2025-10-10 22:30:00+00:00",
      "pnl": 3.2516813999999976,
      "close_reason": "STOP_LOSS"
    },
    {
      "ticket": 73,
      "side": "SELL",
      "open_price": 3783.33,
      "close_price": 3714.5027,
      "open_time": "2025-10-11 22:00:00+00:00",
      "close_time": "2025-10-12 00:15:00+00:00",
      "pnl": 2.0648189999999977,
      "close_reason": "STOP_LOSS"
    },
    {
      "ticket": 74,
      "side": "BUY",
      "open_price": 3819.01,
      "close_price": 3997.01951,
      "open_time": "2025-10-12 09:00:00+00:00",
      "close_time": "2025-10-12 18:30:00+00:00",
      "pnl": 1.7800950999999987,
      "close_reason": "STOP_LOSS"
    },
    {
      "ticket": 75,
      "side": "SELL",
      "open_price": 4122.15,
      "close_price": 3966.43194,
      "open_time": "2025-10-14 07:30:00+00:00",
      "close_time": "2025-10-14 14:00:00+00:00",
      "pnl": 1.557180599999997,
      "close_reason": "STOP_LOSS"
    },
    {
      "ticket": 76,
      "side": "BUY",
      "open_price": 4172.37,
      "close_price": 4059.48,
      "open_time": "2025-10-15 11:15:00+00:00",
      "close_time": "2025-10-15 16:30:00+00:00",
      "pnl": -2.2577999999999974,
      "close_reason": "STOP_LOSS"
    },
    {
      "ticket": 77,
      "side": "BUY",
      "open_price": 4040.49,
      "close_price": 3925.99,
      "open_time": "2025-10-16 09:45:00+00:00",
      "close_time": "2025-10-16 18:45:00+00:00",
      "pnl": -2.29,
      "close_reason": "STOP_LOSS"
    },
    {
      "ticket": 78,
      "side": "SELL",
      "open_price": 3864.97,
      "close_price": 3746.54559,
      "open_time": "2025-10-17 09:15:00+00:00",
      "close_time": "2025-10-17 12:30:00+00:00",
      "pnl": 4.736976399999985,
      "close_reason": "STOP_LOSS"
    },
    {
      "ticket": 79,
      "side": "SELL",
      "open_price": 3752.86,
      "close_price": 3833.9527608016583,
      "open_time": "2025-10-17 16:30:00+00:00",
      "close_time": "2025-10-17 19:00:00+00:00",
      "pnl": -2.4327828240497453,
      "close_reason": "STOP_LOSS"
    },
    {
      "ticket": 80,
      "side": "BUY",
      "open_price": 3908.04,
      "close_price": 3981.58463,
      "open_time": "2025-10-18 10:00:00+00:00",
      "close_time": "2025-10-19 22:00:00+00:00",
      "pnl": 1.4708925999999973,
      "close_reason": "STOP_LOSS"
    },
    {
      "ticket": 81,
      "side": "BUY",
      "open_price": 4039.44,
      "close_price": 3907.32,
      "open_time": "2025-10-20 07:30:00+00:00",
      "close_time": "2025-10-21 07:00:00+00:00",
      "pnl": -2.642399999999998,
      "close_reason": "STOP_LOSS"
    },
    {
      "ticket": 82,
      "side": "SELL",
      "open_price": 3877.42,
      "close_price": 4002.01,
      "open_time": "2025-10-21 07:00:00+00:00",
      "close_time": "2025-10-21 17:45:00+00:00",
      "pnl": -2.491800000000003,
      "close_reason": "STOP_LOSS"
    },
    {
      "ticket": 83,
      "side": "BUY",
      "open_price": 3843.49,
      "close_price": 3960.05054,
      "open_time": "2025-10-23 07:30:00+00:00",
      "close_time": "2025-10-24 10:30:00+00:00",
      "pnl": 1.165605400000004,
      "close_reason": "STOP_LOSS"
    },
    {
      "ticket": 84,
      "side": "BUY",
      "open_price": 3947.48,
      "close_price": 4060.9149,
      "open_time": "2025-10-24 10:30:00+00:00",
      "close_time": "2025-10-26 18:00:00+00:00",
      "pnl": 1.134349000000002,
      "close_reason": "STOP_LOSS"
    },
    {
      "ticket": 85,
      "side": "BUY",
      "open_price": 4228.58,
      "close_price": 4053.79,
      "open_time": "2025-10-27 08:00:00+00:00",
      "close_time": "2025-10-28 22:15:00+00:00",
      "pnl": -1.7478999999999996,
      "close_reason": "STOP_LOSS"
    },
    {
      "ticket": 86,
      "side": "BUY",
      "open_price": 4009.29,
      "close_price": 3930.98,
      "open_time": "2025-10-29 07:15:00+00:00",
      "close_time": "2025-10-29 19:00:00+00:00",
      "pnl": -1.566199999999999,
      "close_reason": "STOP_LOSS"
    },
    {
      "ticket": 87,
      "side": "SELL",
      "open_price": 3855.13,
      "close_price": 3724.89122,
      "open_time": "2025-10-30 07:15:00+00:00",
      "close_time": "2025-10-30 23:30:00+00:00",
      "pnl": 2.6047756000000026,
      "close_reason": "STOP_LOSS"
    },
    {
      "ticket": 88,
      "side": "BUY",
      "open_price": 3862.43,
      "close_price": 3745.92,
      "open_time": "2025-10-31 07:00:00+00:00",
      "close_time": "2025-11-03 05:00:00+00:00",
      "pnl": -2.330199999999995,
      "close_reason": "STOP_LOSS"
    },
    {
      "ticket": 89,
      "side": "SELL",
      "open_price": 3708.11,
      "close_price": 3525.94822,
      "open_time": "2025-11-03 08:30:00+00:00",
      "close_time": "2025-11-04 08:15:00+00:00",
      "pnl": 1.8216177999999987,
      "close_reason": "STOP_LOSS"
    },
    {
      "ticket": 90,
      "side": "SELL",
      "open_price": 3532.2,
      "close_price": 3059.7,
      "open_time": "2025-11-04 08:15:00+00:00",
      "close_time": "2025-11-04 23:30:00+00:00",
      "pnl": 9.450000000000001,
      "close_reason": "TAKE_PROFIT"
    },
    {
      "ticket": 91,
      "side": "SELL",
      "open_price": 3370.71,
      "close_price": 3301.10614,
      "open_time": "2025-11-06 09:30:00+00:00",
      "close_time": "2025-11-06 19:00:00+00:00",
      "pnl": 2.088115800000005,
      "close_reason": "STOP_LOSS"
    },
    {
      "ticket": 92,
      "side": "SELL",
      "open_price": 3290.9,
      "close_price": 3353.9692168355696,
      "open_time": "2025-11-07 03:30:00+00:00",
      "close_time": "2025-11-07 05:00:00+00:00",
      "pnl": -2.522768673422779,
      "close_reason": "STOP_LOSS"
    },
    {
      "ticket": 93,
      "side": "BUY",
      "open_price": 3365.44,
      "close_price": 3274.75,
      "open_time": "2025-11-07 07:45:00+00:00",
      "close_time": "2025-11-07 12:15:00+00:00",
      "pnl": -1.8138000000000012,
      "close_reason": "STOP_LOSS"
    },
    {
      "ticket": 94,
      "side": "SELL",
      "open_price": 3445.61,
      "close_price": 3401.03765,
      "open_time": "2025-11-08 07:00:00+00:00",
      "close_time": "2025-11-08 16:30:00+00:00",
      "pnl": 2.228617499999996,
      "close_reason": "STOP_LOSS"
    },
    {
      "ticket": 95,
      "side": "BUY",
      "open_price": 3401.3,
      "close_price": 3369.562946718103,
      "open_time": "2025-11-08 23:15:00+00:00",
      "close_time": "2025-11-09 04:45:00+00:00",
      "pnl": -2.2215937297328083,
      "close_reason": "STOP_LOSS"
    },
    {
      "ticket": 96,
      "side": "BUY",
      "open_price": 3415.35,
      "close_price": 3523.52334,
      "open_time": "2025-11-09 09:30:00+00:00",
      "close_time": "2025-11-09 16:30:00+00:00",
      "pnl": 4.326933600000011,
      "close_reason": "STOP_LOSS"
    },
    {
      "ticket": 97,
      "side": "BUY",
      "open_price": 3486.2,
      "close_price": 3554.9081,
      "open_time": "2025-11-12 11:00:00+00:00",
      "close_time": "2025-11-12 16:30:00+00:00",
      "pnl": 2.0612430000000086,
      "close_reason": "STOP_LOSS"
    },
    {
      "ticket": 98,
      "side": "BUY",
      "open_price": 3536.12,
      "close_price": 3375.8,
      "open_time": "2025-11-13 10:00:00+00:00",
      "close_time": "2025-11-13 17:45:00+00:00",
      "pnl": -1.603199999999997,
      "close_reason": "STOP_LOSS"
    },
    {
      "ticket": 99,
      "side": "BUY",
      "open_price": 3213.53,
      "close_price": 3130.57,
      "open_time": "2025-11-16 11:00:00+00:00",
      "close_time": "2025-11-16 17:45:00+00:00",
      "pnl": -2.488800000000001,
      "close_reason": "STOP_LOSS"
    },
    {
      "ticket": 100,
      "side": "BUY",
      "open_price": 3195.56,
      "close_price": 3002.94,
      "open_time": "2025-11-17 09:00:00+00:00",
      "close_time": "2025-11-17 21:30:00+00:00",
      "pnl": -1.926199999999999,
      "close_reason": "STOP_LOSS"
    },
    {
      "ticket": 101,
      "side": "BUY",
      "open_price": 3057.1,
      "close_price": 3126.46185,
      "open_time": "2025-11-18 10:30:00+00:00",
      "close_time": "2025-11-18 22:45:00+00:00",
      "pnl": 1.3872370000000047,
      "close_reason": "STOP_LOSS"
    },
    {
      "ticket": 102,
      "side": "SELL",
      "open_price": 3037.96,
      "close_price": 2919.71545,
      "open_time": "2025-11-19 07:00:00+00:00",
      "close_time": "2025-11-19 22:30:00+00:00",
      "pnl": 2.364890999999998,
      "close_reason": "STOP_LOSS"
    },
    {
      "ticket": 103,
      "side": "SELL",
      "open_price": 2810.13,
      "close_price": 2719.3057,
      "open_time": "2025-11-21 04:30:00+00:00",
      "close_time": "2025-11-21 13:00:00+00:00",
      "pnl": 3.632972000000009,
      "close_reason": "STOP_LOSS"
    },
    {
      "ticket": 104,
      "side": "BUY",
      "open_price": 2878.71,
      "close_price": 3006.49866,
      "open_time": "2025-11-24 07:00:00+00:00",
      "close_time": "2025-11-27 02:00:00+00:00",
      "pnl": 2.5557732000000035,
      "close_reason": "STOP_LOSS"
    },
    {
      "ticket": 105,
      "side": "BUY",
      "open_price": 3064.08,
      "close_price": 2992.92,
      "open_time": "2025-11-28 10:45:00+00:00",
      "close_time": "2025-11-29 08:30:00+00:00",
      "pnl": -2.1347999999999954,
      "close_reason": "STOP_LOSS"
    },
    {
      "ticket": 106,
      "side": "SELL",
      "open_price": 3005.7,
      "close_price": 2982.66648,
      "open_time": "2025-11-29 10:00:00+00:00",
      "close_time": "2025-11-29 20:30:00+00:00",
      "pnl": 1.1516759999999977,
      "close_reason": "STOP_LOSS"
    },
    {
      "ticket": 107,
      "side": "BUY",
      "open_price": 3058.7,
      "close_price": 3204.09993,
      "open_time": "2025-12-03 07:30:00+00:00",
      "close_time": "2025-12-04 03:15:00+00:00",
      "pnl": 4.361997900000001,
      "close_reason": "STOP_LOSS"
    },
    {
      "ticket": 108,
      "side": "SELL",
      "open_price": 3112.95,
      "close_price": 3054.9101,
      "open_time": "2025-12-05 11:30:00+00:00",
      "close_time": "2025-12-05 20:00:00+00:00",
      "pnl": 1.7411969999999928,
      "close_reason": "STOP_LOSS"
    },
    {
      "ticket": 109,
      "side": "SELL",
      "open_price": 3014.21,
      "close_price": 3036.469939973984,
      "open_time": "2025-12-06 10:15:00+00:00",
      "close_time": "2025-12-06 12:15:00+00:00",
      "pnl": -2.671192796878058,
      "close_reason": "STOP_LOSS"
    },
    {
      "ticket": 110,
      "side": "SELL",
      "open_price": 3027.91,
      "close_price": 3043.917890732044,
      "open_time": "2025-12-07 10:00:00+00:00",
      "close_time": "2025-12-07 14:45:00+00:00",
      "pnl": -2.561262517127034,
      "close_reason": "STOP_LOSS"
    },
    {
      "ticket": 111,
      "side": "SELL",
      "open_price": 3024.22,
      "close_price": 2941.080646635582,
      "open_time": "2025-12-07 16:00:00+00:00",
      "close_time": "2025-12-07 16:15:00+00:00",
      "pnl": 9.976722403730127,
      "close_reason": "TAKE_PROFIT"
    },
    {
      "ticket": 112,
      "side": "BUY",
      "open_price": 3142.63,
      "close_price": 3343.87211,
      "open_time": "2025-12-08 10:45:00+00:00",
      "close_time": "2025-12-09 22:15:00+00:00",
      "pnl": 4.024842199999994,
      "close_reason": "STOP_LOSS"
    },
    {
      "ticket": 113,
      "side": "BUY",
      "open_price": 3346.72,
      "close_price": 3391.63768,
      "open_time": "2025-12-10 11:45:00+00:00",
      "close_time": "2025-12-10 22:15:00+00:00",
      "pnl": 2.245884000000001,
      "close_reason": "STOP_LOSS"
    },
    {
      "ticket": 114,
      "side": "BUY",
      "open_price": 3118.26,
      "close_price": 3077.29,
      "open_time": "2025-12-13 11:00:00+00:00",
      "close_time": "2025-12-14 13:30:00+00:00",
      "pnl": -2.867900000000018,
      "close_reason": "STOP_LOSS"
    },
    {
      "ticket": 115,
      "side": "BUY",
      "open_price": 3152.48,
      "close_price": 3025.21,
      "open_time": "2025-12-15 11:45:00+00:00",
      "close_time": "2025-12-15 17:00:00+00:00",
      "pnl": -2.5454,
      "close_reason": "STOP_LOSS"
    },
    {
      "ticket": 116,
      "side": "SELL",
      "open_price": 2922.51,
      "close_price": 2972.98,
      "open_time": "2025-12-17 07:15:00+00:00",
      "close_time": "2025-12-17 16:45:00+00:00",
      "pnl": -2.52349999999999,
      "close_reason": "STOP_LOSS"
    },
    {
      "ticket": 117,
      "side": "BUY",
      "open_price": 2946.77,
      "close_price": 3056.44309,
      "open_time": "2025-12-19 08:45:00+00:00",
      "close_time": "2026-01-02 17:15:00+00:00",
      "pnl": 2.1934618000000046,
      "close_reason": "STOP_LOSS"
    },
    {
      "ticket": 118,
      "side": "SELL",
      "open_price": 3113.25,
      "close_price": 3092.69817,
      "open_time": "2026-01-03 07:00:00+00:00",
      "close_time": "2026-01-03 09:30:00+00:00",
      "pnl": 1.8496646999999893,
      "close_reason": "STOP_LOSS"
    },
    {
      "ticket": 119,
      "side": "BUY",
      "open_price": 3236.59,
      "close_price": 3287.10317,
      "open_time": "2026-01-06 13:00:00+00:00",
      "close_time": "2026-01-06 16:30:00+00:00",
      "pnl": 6.061580399999966,
      "close_reason": "STOP_LOSS"
    },
    {
      "ticket": 120,
      "side": "SELL",
      "open_price": 3233.67,
      "close_price": 3155.40252,
      "open_time": "2026-01-07 11:00:00+00:00",
      "close_time": "2026-01-08 00:30:00+00:00",
      "pnl": 3.130699199999999,
      "close_reason": "STOP_LOSS"
    },
    {
      "ticket": 121,
      "side": "SELL",
      "open_price": 3130.89,
      "close_price": 3078.95014,
      "open_time": "2026-01-08 08:00:00+00:00",
      "close_time": "2026-01-08 16:45:00+00:00",
      "pnl": 3.116391599999997,
      "close_reason": "STOP_LOSS"
    },
    {
      "ticket": 122,
      "side": "SELL",
      "open_price": 3104.0,
      "close_price": 3129.983785386726,
      "open_time": "2026-01-09 02:15:00+00:00",
      "close_time": "2026-01-09 03:15:00+00:00",
      "pnl": -3.118054246407137,
      "close_reason": "STOP_LOSS"
    },
    {
      "ticket": 123,
      "side": "BUY",
      "open_price": 3127.02,
      "close_price": 3191.76071,
      "open_time": "2026-01-13 08:00:00+00:00",
      "close_time": "2026-01-13 22:30:00+00:00",
      "pnl": 5.179256800000003,
      "close_reason": "STOP_LOSS"
    },
    {
      "ticket": 124,
      "side": "BUY",
      "open_price": 3321.25,
      "close_price": 3346.66027,
      "open_time": "2026-01-18 11:15:00+00:00",
      "close_time": "2026-01-18 21:45:00+00:00",
      "pnl": 3.0492323999999824,
      "close_reason": "STOP_LOSS"
    },
    {
      "ticket": 125,
      "side": "SELL",
      "open_price": 3197.62,
      "close_price": 3189.48982,
      "open_time": "2026-01-20 00:00:00+00:00",
      "close_time": "2026-01-20 01:30:00+00:00",
      "pnl": 1.3821306000000186,
      "close_reason": "STOP_LOSS"
    },
    {
      "ticket": 126,
      "side": "SELL",
      "open_price": 3155.82,
      "close_price": 3085.4933,
      "open_time": "2026-01-20 07:00:00+00:00",
      "close_time": "2026-01-20 16:30:00+00:00",
      "pnl": 4.2196020000000045,
      "close_reason": "STOP_LOSS"
    },
    {
      "ticket": 127,
      "side": "SELL",
      "open_price": 2957.94,
      "close_price": 2928.86919,
      "open_time": "2026-01-21 10:30:00+00:00",
      "close_time": "2026-01-21 14:45:00+00:00",
      "pnl": 4.069913400000024,
      "close_reason": "STOP_LOSS"
    },
    {
      "ticket": 128,
      "side": "SELL",
      "open_price": 2938.66,
      "close_price": 2983.59,
      "open_time": "2026-01-23 08:45:00+00:00",
      "close_time": "2026-01-23 19:15:00+00:00",
      "pnl": -3.5944000000000234,
      "close_reason": "STOP_LOSS"
    },
    {
      "ticket": 129,
      "side": "SELL",
      "open_price": 2935.82,
      "close_price": 2798.920000000002,
      "open_time": "2026-01-25 08:00:00+00:00",
      "close_time": "2026-01-25 21:45:00+00:00",
      "pnl": 17.796999999999777,
      "close_reason": "TAKE_PROFIT"
    },
    {
      "ticket": 130,
      "side": "BUY",
      "open_price": 2903.2,
      "close_price": 3007.61642,
      "open_time": "2026-01-26 09:45:00+00:00",
      "close_time": "2026-01-28 03:30:00+00:00",
      "pnl": 3.1324926000000004,
      "close_reason": "STOP_LOSS"
    },
    {
      "ticket": 131,
      "side": "SELL",
      "open_price": 2988.91,
      "close_price": 3033.78,
      "open_time": "2026-01-28 11:00:00+00:00",
      "close_time": "2026-01-28 12:15:00+00:00",
      "pnl": -4.038300000000031,
      "close_reason": "STOP_LOSS"
    },
    {
      "ticket": 132,
      "side": "SELL",
      "open_price": 2398.31,
      "close_price": 2337.03399,
      "open_time": "2026-02-01 09:00:00+00:00",
      "close_time": "2026-02-01 20:00:00+00:00",
      "pnl": 3.0638005000000024,
      "close_reason": "STOP_LOSS"
    },
    {
      "ticket": 133,
      "side": "SELL",
      "open_price": 2317.0,
      "close_price": 2294.22625,
      "open_time": "2026-02-02 22:30:00+00:00",
      "close_time": "2026-02-03 14:00:00+00:00",
      "pnl": 2.049637499999985,
      "close_reason": "STOP_LOSS"
    },
    {
      "ticket": 134,
      "side": "BUY",
      "open_price": 1957.4,
      "close_price": 1961.97,
      "open_time": "2026-02-06 07:45:00+00:00",
      "close_time": "2026-03-01 00:00:00+00:00",
      "pnl": 0.09139999999999873,
      "close_reason": "END_OF_BACKTEST"
    }
  ]
}