{
  "symbol": "NZDUSD",
  "start_date": "2025-08-04 02:00:00+00:00",
  "end_date": "2026-03-27 00:00:00+00:00",
  "initial_capital": 50.0,
  "final_equity": 45.996835350350075,
  "total_return_pct": -8.00632929929985,
  "max_drawdown_pct": 8.00632929929985,
  "win_rate": 0.0,
  "profit_factor": 0.0,
  "total_trades": 232,
  "avg_trade_pnl": -0.017255020041594522,
  "sharpe_ratio": -0.6557162776220462,
  "sortino_ratio": -0.08446168624420236,
  "max_consecutive_losses": 232,
  "max_consecutive_wins": 0,
  "avg_trade_duration_hours": 2.266522988505747,
  "best_trade_pnl": 0.0,
  "worst_trade_pnl": -0.1033862062236438,
  "expectancy": -0.017255020041594522,
  "strategy": "M5KeltnerSqueezeStrategy",
  "trades": [
    {
      "ticket": 1,
      "side": "SELL",
      "open_price": 0.5824293654522597,
      "close_price": 0.5903821505463861,
      "open_time": "2025-08-04 20:40:00+00:00",
      "close_time": "2025-08-04 21:00:00+00:00",
      "pnl": -0.1033862062236438,
      "close_reason": "STOP_LOSS"
    },
    {
      "ticket": 2,
      "side": "SELL",
      "open_price": 0.5881696693406936,
      "close_price": 0.5950717974979726,
      "open_time": "2025-08-07 14:40:00+00:00",
      "close_time": "2025-08-07 14:55:00+00:00",
      "pnl": -0.062119153415510775,
      "close_reason": "STOP_LOSS"
    },
    {
      "ticket": 3,
      "side": "BUY",
      "open_price": 0.6028363765178694,
      "close_price": 0.5949322940908159,
      "open_time": "2025-08-07 16:55:00+00:00",
      "close_time": "2025-08-07 17:00:00+00:00",
      "pnl": -0.06323265941642742,
      "close_reason": "STOP_LOSS"
    },
    {
      "ticket": 4,
      "side": "SELL",
      "open_price": 0.5853911052952707,
      "close_price": 0.5929695162352822,
      "open_time": "2025-08-11 17:50:00+00:00",
      "close_time": "2025-08-11 18:00:00+00:00",
      "pnl": -0.0606272875200915,
      "close_reason": "STOP_LOSS"
    },
    {
      "ticket": 5,
      "side": "SELL",
      "open_price": 0.5849390053516841,
      "close_price": 0.5935666004393353,
      "open_time": "2025-08-12 10:45:00+00:00",
      "close_time": "2025-08-12 10:50:00+00:00",
      "pnl": -0.06039316561355846,
      "close_reason": "STOP_LOSS"
    },
    {
      "ticket": 6,
      "side": "SELL",
      "open_price": 0.5846855452988985,
      "close_price": 0.5915337714401268,
      "open_time": "2025-08-12 11:20:00+00:00",
      "close_time": "2025-08-12 14:25:00+00:00",
      "pnl": -0.047937582988597856,
      "close_reason": "TAKE_PROFIT"
    },
    {
      "ticket": 7,
      "side": "SELL",
      "open_price": 0.5909670912394007,
      "close_price": 0.5984357078179356,
      "open_time": "2025-08-13 15:35:00+00:00",
      "close_time": "2025-08-13 17:25:00+00:00",
      "pnl": -0.059748932628279405,
      "close_reason": "STOP_LOSS"
    },
    {
      "ticket": 8,
      "side": "SELL",
      "open_price": 0.5867975906712084,
      "close_price": 0.5915246970733314,
      "open_time": "2025-08-14 15:30:00+00:00",
      "close_time": "2025-08-14 17:10:00+00:00",
      "pnl": -0.037816851216984304,
      "close_reason": "TAKE_PROFIT"
    },
    {
      "ticket": 9,
      "side": "SELL",
      "open_price": 0.5746400774391608,
      "close_price": 0.5828938824723674,
      "open_time": "2025-08-20 10:20:00+00:00",
      "close_time": "2025-08-20 11:50:00+00:00",
      "pnl": -0.06603044026565286,
      "close_reason": "STOP_LOSS"
    },
    {
      "ticket": 10,
      "side": "SELL",
      "open_price": 0.5732043179077807,
      "close_price": 0.581025305123629,
      "open_time": "2025-08-22 08:00:00+00:00",
      "close_time": "2025-08-22 10:50:00+00:00",
      "pnl": -0.06256789772678673,
      "close_reason": "STOP_LOSS"
    },
    {
      "ticket": 11,
      "side": "SELL",
      "open_price": 0.573518630265684,
      "close_price": 0.5809550477286859,
      "open_time": "2025-08-22 10:45:00+00:00",
      "close_time": "2025-08-22 10:50:00+00:00",
      "pnl": -0.059491339704015544,
      "close_reason": "STOP_LOSS"
    },
    {
      "ticket": 12,
      "side": "SELL",
      "open_price": 0.5768933393538778,
      "close_price": 0.5847792228547054,
      "open_time": "2025-08-27 09:20:00+00:00",
      "close_time": "2025-08-27 09:25:00+00:00",
      "pnl": -0.06308706800662112,
      "close_reason": "STOP_LOSS"
    },
    {
      "ticket": 13,
      "side": "SELL",
      "open_price": 0.5750268411177816,
      "close_price": 0.582854659710692,
      "open_time": "2025-08-27 10:10:00+00:00",
      "close_time": "2025-08-27 11:25:00+00:00",
      "pnl": -0.054794730150372624,
      "close_reason": "TAKE_PROFIT"
    },
    {
      "ticket": 14,
      "side": "SELL",
      "open_price": 0.5748865560126736,
      "close_price": 0.5826983507920651,
      "open_time": "2025-08-27 15:05:00+00:00",
      "close_time": "2025-08-27 15:15:00+00:00",
      "pnl": -0.062494358235132275,
      "close_reason": "STOP_LOSS"
    },
    {
      "ticket": 15,
      "side": "BUY",
      "open_price": 0.5913431122914161,
      "close_price": 0.584908060261614,
      "open_time": "2025-08-27 17:50:00+00:00",
      "close_time": "2025-08-27 19:10:00+00:00",
      "pnl": -0.04504536420861472,
      "close_reason": "TAKE_PROFIT"
    },
    {
      "ticket": 16,
      "side": "BUY",
      "open_price": 0.5945809491212686,
      "close_price": 0.5872053342628476,
      "open_time": "2025-08-28 15:10:00+00:00",
      "close_time": "2025-08-28 15:30:00+00:00",
      "pnl": -0.059004918867367806,
      "close_reason": "STOP_LOSS"
    },
    {
      "ticket": 17,
      "side": "SELL",
      "open_price": 0.5781792657384188,
      "close_price": 0.5853610479353905,
      "open_time": "2025-09-02 14:30:00+00:00",
      "close_time": "2025-09-02 14:40:00+00:00",
      "pnl": -0.06463603977274468,
      "close_reason": "STOP_LOSS"
    },
    {
      "ticket": 18,
      "side": "SELL",
      "open_price": 0.5769015882827826,
      "close_price": 0.5851998913475807,
      "open_time": "2025-09-02 15:20:00+00:00",
      "close_time": "2025-09-02 16:35:00+00:00",
      "pnl": -0.0663864245183845,
      "close_reason": "STOP_LOSS"
    },
    {
      "ticket": 19,
      "side": "SELL",
      "open_price": 0.5773710647580375,
      "close_price": 0.5865570283292448,
      "open_time": "2025-09-04 10:50:00+00:00",
      "close_time": "2025-09-04 11:05:00+00:00",
      "pnl": -0.06430174499845165,
      "close_reason": "STOP_LOSS"
    },
    {
      "ticket": 20,
      "side": "SELL",
      "open_price": 0.5790970917002272,
      "close_price": 0.5867160971469231,
      "open_time": "2025-09-04 11:15:00+00:00",
      "close_time": "2025-09-04 11:40:00+00:00",
      "pnl": -0.060952043573567316,
      "close_reason": "STOP_LOSS"
    },
    {
      "ticket": 21,
      "side": "SELL",
      "open_price": 0.5774688328834691,
      "close_price": 0.585673351532101,
      "open_time": "2025-09-04 15:20:00+00:00",
      "close_time": "2025-09-04 16:00:00+00:00",
      "pnl": -0.06563614918905536,
      "close_reason": "STOP_LOSS"
    },
    {
      "ticket": 22,
      "side": "BUY",
      "open_price": 0.5939878380714423,
      "close_price": 0.5873145225522542,
      "open_time": "2025-09-05 14:20:00+00:00",
      "close_time": "2025-09-05 14:25:00+00:00",
      "pnl": -0.06005983967269235,
      "close_reason": "STOP_LOSS"
    },
    {
      "ticket": 23,
      "side": "SELL",
      "open_price": 0.5844031174744593,
      "close_price": 0.5936309366664622,
      "open_time": "2025-09-08 19:35:00+00:00",
      "close_time": "2025-09-08 21:20:00+00:00",
      "pnl": -0.06459473434402019,
      "close_reason": "STOP_LOSS"
    },
    {
      "ticket": 24,
      "side": "SELL",
      "open_price": 0.585935495567904,
      "close_price": 0.592206010827381,
      "open_time": "2025-09-09 17:25:00+00:00",
      "close_time": "2025-09-09 21:45:00+00:00",
      "pnl": -0.04389360681633881,
      "close_reason": "TAKE_PROFIT"
    },
    {
      "ticket": 26,
      "side": "SELL",
      "open_price": 0.5837308062951412,
      "close_price": 0.5928477297456313,
      "open_time": "2025-09-09 20:55:00+00:00",
      "close_time": "2025-09-10 01:45:00+00:00",
      "pnl": -0.06381846415343062,
      "close_reason": "STOP_LOSS"
    },
    {
      "ticket": 25,
      "side": "SELL",
      "open_price": 0.5849070835448436,
      "close_price": 0.5941582557919682,
      "open_time": "2025-09-09 17:35:00+00:00",
      "close_time": "2025-09-10 06:45:00+00:00",
      "pnl": -0.06475820572987279,
      "close_reason": "STOP_LOSS"
    },
    {
      "ticket": 27,
      "side": "SELL",
      "open_price": 0.5848479871785195,
      "close_price": 0.5941593991979579,
      "open_time": "2025-09-10 11:20:00+00:00",
      "close_time": "2025-09-10 12:10:00+00:00",
      "pnl": -0.0651798841360689,
      "close_reason": "STOP_LOSS"
    },
    {
      "ticket": 28,
      "side": "SELL",
      "open_price": 0.5851382377137664,
      "close_price": 0.5927262108364342,
      "open_time": "2025-09-11 08:05:00+00:00",
      "close_time": "2025-09-11 11:20:00+00:00",
      "pnl": -0.05311581185867454,
      "close_reason": "TAKE_PROFIT"
    },
    {
      "ticket": 29,
      "side": "SELL",
      "open_price": 0.5839523635060352,
      "close_price": 0.5930289338742518,
      "open_time": "2025-09-11 11:20:00+00:00",
      "close_time": "2025-09-11 11:45:00+00:00",
      "pnl": -0.06353599257751641,
      "close_reason": "STOP_LOSS"
    },
    {
      "ticket": 30,
      "side": "SELL",
      "open_price": 0.5841101679439586,
      "close_price": 0.5928317171138521,
      "open_time": "2025-09-11 12:05:00+00:00",
      "close_time": "2025-09-11 13:00:00+00:00",
      "pnl": -0.061050844189254,
      "close_reason": "STOP_LOSS"
    },
    {
      "ticket": 31,
      "side": "BUY",
      "open_price": 0.6055003141767994,
      "close_price": 0.5971771515875572,
      "open_time": "2025-09-11 21:45:00+00:00",
      "close_time": "2025-09-12 00:00:00+00:00",
      "pnl": -0.0665853007139372,
      "close_reason": "STOP_LOSS"
    },
    {
      "ticket": 32,
      "side": "SELL",
      "open_price": 0.5878136819704671,
      "close_price": 0.5966739963895661,
      "open_time": "2025-09-12 09:20:00+00:00",
      "close_time": "2025-09-12 09:55:00+00:00",
      "pnl": -0.06202220093369271,
      "close_reason": "STOP_LOSS"
    },
    {
      "ticket": 33,
      "side": "SELL",
      "open_price": 0.5895252438396372,
      "close_price": 0.5970354734635523,
      "open_time": "2025-09-17 08:25:00+00:00",
      "close_time": "2025-09-17 09:40:00+00:00",
      "pnl": -0.06008183699132097,
      "close_reason": "TAKE_PROFIT"
    },
    {
      "ticket": 34,
      "side": "SELL",
      "open_price": 0.5886992772471493,
      "close_price": 0.5972649933423283,
      "open_time": "2025-09-17 20:30:00+00:00",
      "close_time": "2025-09-17 20:35:00+00:00",
      "pnl": -0.03426286438071591,
      "close_reason": "STOP_LOSS"
    },
    {
      "ticket": 35,
      "side": "SELL",
      "open_price": 0.5827638776366767,
      "close_price": 0.5884864301725073,
      "open_time": "2025-09-18 15:10:00+00:00",
      "close_time": "2025-09-18 16:30:00+00:00",
      "pnl": -0.028612762679153247,
      "close_reason": "TAKE_PROFIT"
    },
    {
      "ticket": 36,
      "side": "SELL",
      "open_price": 0.5799755054540433,
      "close_price": 0.5881864810753381,
      "open_time": "2025-09-18 18:40:00+00:00",
      "close_time": "2025-09-18 20:05:00+00:00",
      "pnl": -0.04105487810647401,
      "close_reason": "STOP_LOSS"
    },
    {
      "ticket": 37,
      "side": "SELL",
      "open_price": 0.5768770694868263,
      "close_price": 0.5857652149985695,
      "open_time": "2025-09-19 18:35:00+00:00",
      "close_time": "2025-09-19 18:55:00+00:00",
      "pnl": -0.03555258204697287,
      "close_reason": "STOP_LOSS"
    },
    {
      "ticket": 38,
      "side": "BUY",
      "open_price": 0.5938410426465343,
      "close_price": 0.5859373457747868,
      "open_time": "2025-09-23 15:10:00+00:00",
      "close_time": "2025-09-23 15:40:00+00:00",
      "pnl": -0.03951848435873706,
      "close_reason": "STOP_LOSS"
    },
    {
      "ticket": 39,
      "side": "SELL",
      "open_price": 0.5726915177640414,
      "close_price": 0.5813810023323264,
      "open_time": "2025-09-24 19:10:00+00:00",
      "close_time": "2025-09-24 20:10:00+00:00",
      "pnl": -0.03475793827314,
      "close_reason": "STOP_LOSS"
    },
    {
      "ticket": 40,
      "side": "SELL",
      "open_price": 0.5726931247571602,
      "close_price": 0.5814726780669511,
      "open_time": "2025-09-24 20:15:00+00:00",
      "close_time": "2025-09-24 20:35:00+00:00",
      "pnl": -0.035118213239163865,
      "close_reason": "STOP_LOSS"
    },
    {
      "ticket": 41,
      "side": "BUY",
      "open_price": 0.5847186460019546,
      "close_price": 0.5776551196888887,
      "open_time": "2025-09-26 19:10:00+00:00",
      "close_time": "2025-09-29 00:00:00+00:00",
      "pnl": -0.02825410525226335,
      "close_reason": "TAKE_PROFIT"
    },
    {
      "ticket": 42,
      "side": "BUY",
      "open_price": 0.5849913614529978,
      "close_price": 0.5783078122534406,
      "open_time": "2025-09-26 19:25:00+00:00",
      "close_time": "2025-09-29 05:45:00+00:00",
      "pnl": -0.0334177459977858,
      "close_reason": "TAKE_PROFIT"
    },
    {
      "ticket": 43,
      "side": "BUY",
      "open_price": 0.5873467127424304,
      "close_price": 0.5789132188967433,
      "open_time": "2025-09-29 10:50:00+00:00",
      "close_time": "2025-09-29 11:20:00+00:00",
      "pnl": -0.03373397538274858,
      "close_reason": "STOP_LOSS"
    },
    {
      "ticket": 44,
      "side": "BUY",
      "open_price": 0.5881060550365965,
      "close_price": 0.5789763664390907,
      "open_time": "2025-09-30 09:10:00+00:00",
      "close_time": "2025-09-30 10:40:00+00:00",
      "pnl": -0.03651875439002339,
      "close_reason": "STOP_LOSS"
    },
    {
      "ticket": 45,
      "side": "BUY",
      "open_price": 0.5869940470161599,
      "close_price": 0.5790586128892243,
      "open_time": "2025-09-30 09:20:00+00:00",
      "close_time": "2025-09-30 10:40:00+00:00",
      "pnl": -0.03967717063467768,
      "close_reason": "STOP_LOSS"
    },
    {
      "ticket": 46,
      "side": "BUY",
      "open_price": 0.5888310240328755,
      "close_price": 0.5799011224339918,
      "open_time": "2025-09-30 11:15:00+00:00",
      "close_time": "2025-09-30 12:00:00+00:00",
      "pnl": -0.03571960639553451,
      "close_reason": "STOP_LOSS"
    },
    {
      "ticket": 47,
      "side": "BUY",
      "open_price": 0.5908064770233968,
      "close_price": 0.5817566160728347,
      "open_time": "2025-10-01 17:20:00+00:00",
      "close_time": "2025-10-01 17:45:00+00:00",
      "pnl": -0.0361994438022486,
      "close_reason": "STOP_LOSS"
    },
    {
      "ticket": 48,
      "side": "BUY",
      "open_price": 0.5910793195089347,
      "close_price": 0.5834459263023895,
      "open_time": "2025-10-02 12:40:00+00:00",
      "close_time": "2025-10-02 12:50:00+00:00",
      "pnl": -0.03816696603272607,
      "close_reason": "STOP_LOSS"
    },
    {
      "ticket": 49,
      "side": "SELL",
      "open_price": 0.576255558551106,
      "close_price": 0.5822855457229088,
      "open_time": "2025-10-02 13:00:00+00:00",
      "close_time": "2025-10-02 15:40:00+00:00",
      "pnl": -0.030149935859014043,
      "close_reason": "TAKE_PROFIT"
    },
    {
      "ticket": 50,
      "side": "BUY",
      "open_price": 0.5898143111253923,
      "close_price": 0.5817856029245532,
      "open_time": "2025-10-02 21:30:00+00:00",
      "close_time": "2025-10-02 22:40:00+00:00",
      "pnl": -0.04014354100419559,
      "close_reason": "STOP_LOSS"
    },
    {
      "ticket": 51,
      "side": "BUY",
      "open_price": 0.5923321965438659,
      "close_price": 0.5836100979900515,
      "open_time": "2025-10-06 19:55:00+00:00",
      "close_time": "2025-10-07 00:00:00+00:00",
      "pnl": -0.0348883942152578,
      "close_reason": "STOP_LOSS"
    },
    {
      "ticket": 52,
      "side": "SELL",
      "open_price": 0.5735277279843227,
      "close_price": 0.5810661510885615,
      "open_time": "2025-10-07 12:40:00+00:00",
      "close_time": "2025-10-07 12:50:00+00:00",
      "pnl": -0.037692115521194,
      "close_reason": "STOP_LOSS"
    },
    {
      "ticket": 53,
      "side": "SELL",
      "open_price": 0.5667566469654157,
      "close_price": 0.5743320454576272,
      "open_time": "2025-10-08 08:25:00+00:00",
      "close_time": "2025-10-08 08:30:00+00:00",
      "pnl": -0.037876992461057246,
      "close_reason": "STOP_LOSS"
    },
    {
      "ticket": 54,
      "side": "SELL",
      "open_price": 0.5653405199277638,
      "close_price": 0.5741948400144385,
      "open_time": "2025-10-08 08:55:00+00:00",
      "close_time": "2025-10-08 09:00:00+00:00",
      "pnl": -0.035417280346699,
      "close_reason": "STOP_LOSS"
    },
    {
      "ticket": 55,
      "side": "BUY",
      "open_price": 0.5869535612447937,
      "close_price": 0.5778835411755464,
      "open_time": "2025-10-08 18:00:00+00:00",
      "close_time": "2025-10-08 18:35:00+00:00",
      "pnl": -0.036280080276989146,
      "close_reason": "STOP_LOSS"
    },
    {
      "ticket": 56,
      "side": "BUY",
      "open_price": 0.586839856883895,
      "close_price": 0.5794080215210894,
      "open_time": "2025-10-08 21:35:00+00:00",
      "close_time": "2025-10-09 04:05:00+00:00",
      "pnl": -0.029727341451222244,
      "close_reason": "TAKE_PROFIT"
    },
    {
      "ticket": 58,
      "side": "SELL",
      "open_price": 0.5652852754346821,
      "close_price": 0.5741555077088671,
      "open_time": "2025-10-09 21:45:00+00:00",
      "close_time": "2025-10-09 22:30:00+00:00",
      "pnl": -0.035480929096740166,
      "close_reason": "STOP_LOSS"
    },
    {
      "ticket": 57,
      "side": "SELL",
      "open_price": 0.5664295175654653,
      "close_price": 0.5745710249142031,
      "open_time": "2025-10-09 20:30:00+00:00",
      "close_time": "2025-10-09 23:25:00+00:00",
      "pnl": -0.040707536743688766,
      "close_reason": "STOP_LOSS"
    },
    {
      "ticket": 59,
      "side": "SELL",
      "open_price": 0.5666894348411143,
      "close_price": 0.5729810617894218,
      "open_time": "2025-10-10 17:45:00+00:00",
      "close_time": "2025-10-10 18:15:00+00:00",
      "pnl": -0.031458134741537136,
      "close_reason": "TAKE_PROFIT"
    },
    {
      "ticket": 60,
      "side": "SELL",
      "open_price": 0.5610169692975249,
      "close_price": 0.5694684786125704,
      "open_time": "2025-10-14 11:05:00+00:00",
      "close_time": "2025-10-14 11:30:00+00:00",
      "pnl": -0.033806037260182276,
      "close_reason": "STOP_LOSS"
    },
    {
      "ticket": 61,
      "side": "BUY",
      "open_price": 0.5768137319082212,
      "close_price": 0.5704079938857373,
      "open_time": "2025-10-14 16:00:00+00:00",
      "close_time": "2025-10-14 17:10:00+00:00",
      "pnl": -0.03202869011241949,
      "close_reason": "TAKE_PROFIT"
    },
    {
      "ticket": 62,
      "side": "BUY",
      "open_price": 0.5803661794480499,
      "close_price": 0.5720208310604623,
      "open_time": "2025-10-15 08:00:00+00:00",
      "close_time": "2025-10-15 08:05:00+00:00",
      "pnl": -0.03338139355035041,
      "close_reason": "STOP_LOSS"
    },
    {
      "ticket": 63,
      "side": "BUY",
      "open_price": 0.5829831245998844,
      "close_price": 0.5740263515210469,
      "open_time": "2025-10-16 08:50:00+00:00",
      "close_time": "2025-10-16 09:00:00+00:00",
      "pnl": -0.035827092315350306,
      "close_reason": "STOP_LOSS"
    },
    {
      "ticket": 64,
      "side": "BUY",
      "open_price": 0.5822300304339231,
      "close_price": 0.5739984095115148,
      "open_time": "2025-10-16 09:45:00+00:00",
      "close_time": "2025-10-16 09:50:00+00:00",
      "pnl": -0.04115810461204128,
      "close_reason": "STOP_LOSS"
    },
    {
      "ticket": 65,
      "side": "SELL",
      "open_price": 0.5628530763465487,
      "close_price": 0.5716963106091324,
      "open_time": "2025-10-17 17:05:00+00:00",
      "close_time": "2025-10-17 17:25:00+00:00",
      "pnl": -0.03537293705033484,
      "close_reason": "STOP_LOSS"
    },
    {
      "ticket": 66,
      "side": "SELL",
      "open_price": 0.5645742082627629,
      "close_price": 0.5721766979108353,
      "open_time": "2025-10-17 18:45:00+00:00",
      "close_time": "2025-10-17 19:00:00+00:00",
      "pnl": -0.03801244824036154,
      "close_reason": "STOP_LOSS"
    },
    {
      "ticket": 67,
      "side": "SELL",
      "open_price": 0.5665243371366018,
      "close_price": 0.5732413587823207,
      "open_time": "2025-10-20 15:20:00+00:00",
      "close_time": "2025-10-20 15:45:00+00:00",
      "pnl": -0.04030212987431381,
      "close_reason": "STOP_LOSS"
    },
    {
      "ticket": 68,
      "side": "SELL",
      "open_price": 0.5645537542298765,
      "close_price": 0.571399633905697,
      "open_time": "2025-10-21 08:25:00+00:00",
      "close_time": "2025-10-21 11:00:00+00:00",
      "pnl": -0.03422939837910255,
      "close_reason": "TAKE_PROFIT"
    },
    {
      "ticket": 69,
      "side": "SELL",
      "open_price": 0.5649951866178335,
      "close_price": 0.5717441944525203,
      "open_time": "2025-10-21 13:35:00+00:00",
      "close_time": "2025-10-21 14:00:00+00:00",
      "pnl": -0.04049404700812076,
      "close_reason": "STOP_LOSS"
    },
    {
      "ticket": 70,
      "side": "BUY",
      "open_price": 0.5795101639107991,
      "close_price": 0.5722467292435807,
      "open_time": "2025-10-21 15:55:00+00:00",
      "close_time": "2025-10-21 16:45:00+00:00",
      "pnl": -0.0363171733360923,
      "close_reason": "STOP_LOSS"
    },
    {
      "ticket": 71,
      "side": "BUY",
      "open_price": 0.5839164442959248,
      "close_price": 0.575537801429676,
      "open_time": "2025-10-22 09:40:00+00:00",
      "close_time": "2025-10-22 10:00:00+00:00",
      "pnl": -0.033514571464995146,
      "close_reason": "STOP_LOSS"
    },
    {
      "ticket": 72,
      "side": "BUY",
      "open_price": 0.5832791518349032,
      "close_price": 0.5755772478824676,
      "open_time": "2025-10-22 09:50:00+00:00",
      "close_time": "2025-10-22 10:00:00+00:00",
      "pnl": -0.0385095197621782,
      "close_reason": "STOP_LOSS"
    },
    {
      "ticket": 73,
      "side": "BUY",
      "open_price": 0.5833518935916853,
      "close_price": 0.5749970253656954,
      "open_time": "2025-10-22 10:05:00+00:00",
      "close_time": "2025-10-22 10:15:00+00:00",
      "pnl": -0.03341947290395941,
      "close_reason": "STOP_LOSS"
    },
    {
      "ticket": 74,
      "side": "SELL",
      "open_price": 0.5671269612489419,
      "close_price": 0.5745789646506682,
      "open_time": "2025-10-22 13:20:00+00:00",
      "close_time": "2025-10-22 17:00:00+00:00",
      "pnl": -0.03726001700863124,
      "close_reason": "STOP_LOSS"
    },
    {
      "ticket": 75,
      "side": "BUY",
      "open_price": 0.5819315279461168,
      "close_price": 0.5743175966788051,
      "open_time": "2025-10-22 17:10:00+00:00",
      "close_time": "2025-10-22 17:25:00+00:00",
      "pnl": -0.038069656336558455,
      "close_reason": "STOP_LOSS"
    },
    {
      "ticket": 76,
      "side": "BUY",
      "open_price": 0.5813364537552066,
      "close_price": 0.5741575774865562,
      "open_time": "2025-10-23 13:40:00+00:00",
      "close_time": "2025-10-23 13:45:00+00:00",
      "pnl": -0.03589438134325218,
      "close_reason": "STOP_LOSS"
    },
    {
      "ticket": 77,
      "side": "SELL",
      "open_price": 0.5668232602945108,
      "close_price": 0.5742135816542528,
      "open_time": "2025-10-23 15:20:00+00:00",
      "close_time": "2025-10-23 15:30:00+00:00",
      "pnl": -0.036951606798710235,
      "close_reason": "STOP_LOSS"
    },
    {
      "ticket": 78,
      "side": "SELL",
      "open_price": 0.5665836833424763,
      "close_price": 0.5743560589076818,
      "open_time": "2025-10-23 15:35:00+00:00",
      "close_time": "2025-10-23 15:40:00+00:00",
      "pnl": -0.03886187782602746,
      "close_reason": "STOP_LOSS"
    },
    {
      "ticket": 79,
      "side": "BUY",
      "open_price": 0.5831090081933514,
      "close_price": 0.5747784554801155,
      "open_time": "2025-10-23 17:40:00+00:00",
      "close_time": "2025-10-23 18:15:00+00:00",
      "pnl": -0.04165276356617953,
      "close_reason": "STOP_LOSS"
    },
    {
      "ticket": 80,
      "side": "SELL",
      "open_price": 0.5688095834470395,
      "close_price": 0.5767297029127952,
      "open_time": "2025-10-28 11:50:00+00:00",
      "close_time": "2025-10-28 12:35:00+00:00",
      "pnl": -0.03960059732877885,
      "close_reason": "STOP_LOSS"
    },
    {
      "ticket": 81,
      "side": "SELL",
      "open_price": 0.5691446137049069,
      "close_price": 0.5755864411258228,
      "open_time": "2025-10-30 12:50:00+00:00",
      "close_time": "2025-10-30 14:40:00+00:00",
      "pnl": -0.03220913710457962,
      "close_reason": "TAKE_PROFIT"
    },
    {
      "ticket": 82,
      "side": "BUY",
      "open_price": 0.5797395886566228,
      "close_price": 0.5720791370988437,
      "open_time": "2025-10-31 13:05:00+00:00",
      "close_time": "2025-10-31 14:35:00+00:00",
      "pnl": -0.03830225778889529,
      "close_reason": "STOP_LOSS"
    },
    {
      "ticket": 83,
      "side": "SELL",
      "open_price": 0.565679998264504,
      "close_price": 0.5726096915920468,
      "open_time": "2025-10-31 16:55:00+00:00",
      "close_time": "2025-10-31 17:00:00+00:00",
      "pnl": -0.034648466637713926,
      "close_reason": "STOP_LOSS"
    },
    {
      "ticket": 84,
      "side": "SELL",
      "open_price": 0.5590358538693538,
      "close_price": 0.5659386486411554,
      "open_time": "2025-11-04 16:30:00+00:00",
      "close_time": "2025-11-04 16:40:00+00:00",
      "pnl": -0.034513973859007785,
      "close_reason": "STOP_LOSS"
    },
    {
      "ticket": 85,
      "side": "SELL",
      "open_price": 0.5595777963908567,
      "close_price": 0.5663828571145523,
      "open_time": "2025-11-04 16:55:00+00:00",
      "close_time": "2025-11-04 17:05:00+00:00",
      "pnl": -0.040830364342173464,
      "close_reason": "STOP_LOSS"
    },
    {
      "ticket": 86,
      "side": "SELL",
      "open_price": 0.5573488305872805,
      "close_price": 0.5642612499472132,
      "open_time": "2025-11-04 21:35:00+00:00",
      "close_time": "2025-11-04 23:40:00+00:00",
      "pnl": -0.03456209679966349,
      "close_reason": "TAKE_PROFIT"
    },
    {
      "ticket": 87,
      "side": "SELL",
      "open_price": 0.5554588586448016,
      "close_price": 0.5635326039807068,
      "open_time": "2025-11-06 19:45:00+00:00",
      "close_time": "2025-11-06 20:25:00+00:00",
      "pnl": -0.04036872667952607,
      "close_reason": "STOP_LOSS"
    },
    {
      "ticket": 89,
      "side": "BUY",
      "open_price": 0.5717394189994863,
      "close_price": 0.5643219085626211,
      "open_time": "2025-11-11 13:10:00+00:00",
      "close_time": "2025-11-11 13:15:00+00:00",
      "pnl": 0.0,
      "close_reason": "STOP_LOSS"
    },
    {
      "ticket": 88,
      "side": "BUY",
      "open_price": 0.5728363577863665,
      "close_price": 0.5642636434579194,
      "open_time": "2025-11-11 12:40:00+00:00",
      "close_time": "2025-11-11 13:20:00+00:00",
      "pnl": -0.03429085731378878,
      "close_reason": "STOP_LOSS"
    },
    {
      "ticket": 90,
      "side": "BUY",
      "open_price": 0.572281800028841,
      "close_price": 0.5652515311280535,
      "open_time": "2025-11-11 13:55:00+00:00",
      "close_time": "2025-11-11 14:10:00+00:00",
      "pnl": 0.0,
      "close_reason": "TAKE_PROFIT"
    },
    {
      "ticket": 92,
      "side": "SELL",
      "open_price": 0.5586864060856166,
      "close_price": 0.5662561736386641,
      "open_time": "2025-11-17 17:15:00+00:00",
      "close_time": "2025-11-17 17:20:00+00:00",
      "pnl": 0.0,
      "close_reason": "STOP_LOSS"
    },
    {
      "ticket": 91,
      "side": "SELL",
      "open_price": 0.5593658786447469,
      "close_price": 0.5667207834835453,
      "open_time": "2025-11-17 16:55:00+00:00",
      "close_time": "2025-11-17 17:55:00+00:00",
      "pnl": 0.0,
      "close_reason": "STOP_LOSS"
    },
    {
      "ticket": 93,
      "side": "SELL",
      "open_price": 0.5585570050740704,
      "close_price": 0.5666968352203174,
      "open_time": "2025-11-17 17:25:00+00:00",
      "close_time": "2025-11-17 17:55:00+00:00",
      "pnl": 0.0,
      "close_reason": "STOP_LOSS"
    },
    {
      "ticket": 94,
      "side": "BUY",
      "open_price": 0.5742434983806252,
      "close_price": 0.5668763956877537,
      "open_time": "2025-11-18 12:25:00+00:00",
      "close_time": "2025-11-18 15:20:00+00:00",
      "pnl": 0.0,
      "close_reason": "TAKE_PROFIT"
    },
    {
      "ticket": 95,
      "side": "SELL",
      "open_price": 0.5552028771893174,
      "close_price": 0.5635728609671916,
      "open_time": "2025-11-19 08:00:00+00:00",
      "close_time": "2025-11-19 08:10:00+00:00",
      "pnl": 0.0,
      "close_reason": "STOP_LOSS"
    },
    {
      "ticket": 96,
      "side": "BUY",
      "open_price": 0.5762723326975943,
      "close_price": 0.5684001782329728,
      "open_time": "2025-11-26 08:45:00+00:00",
      "close_time": "2025-11-26 08:55:00+00:00",
      "pnl": 0.0,
      "close_reason": "STOP_LOSS"
    },
    {
      "ticket": 97,
      "side": "SELL",
      "open_price": 0.5585497230330165,
      "close_price": 0.5676223964049841,
      "open_time": "2025-11-26 12:25:00+00:00",
      "close_time": "2025-11-26 15:10:00+00:00",
      "pnl": 0.0,
      "close_reason": "STOP_LOSS"
    },
    {
      "ticket": 98,
      "side": "BUY",
      "open_price": 0.5768871299473362,
      "close_price": 0.5691531769184259,
      "open_time": "2025-11-26 20:15:00+00:00",
      "close_time": "2025-11-27 00:10:00+00:00",
      "pnl": 0.0,
      "close_reason": "STOP_LOSS"
    },
    {
      "ticket": 99,
      "side": "BUY",
      "open_price": 0.5808378895680305,
      "close_price": 0.57222747170287,
      "open_time": "2025-11-27 08:00:00+00:00",
      "close_time": "2025-11-27 08:15:00+00:00",
      "pnl": 0.0,
      "close_reason": "STOP_LOSS"
    },
    {
      "ticket": 100,
      "side": "SELL",
      "open_price": 0.5638694816566481,
      "close_price": 0.5716289304267937,
      "open_time": "2025-11-28 08:50:00+00:00",
      "close_time": "2025-11-28 09:30:00+00:00",
      "pnl": 0.0,
      "close_reason": "STOP_LOSS"
    },
    {
      "ticket": 102,
      "side": "SELL",
      "open_price": 0.5630930403573059,
      "close_price": 0.5708426575561403,
      "open_time": "2025-11-28 12:35:00+00:00",
      "close_time": "2025-11-28 14:25:00+00:00",
      "pnl": 0.0,
      "close_reason": "STOP_LOSS"
    },
    {
      "ticket": 103,
      "side": "SELL",
      "open_price": 0.5632182538185572,
      "close_price": 0.5709742302674924,
      "open_time": "2025-11-28 14:25:00+00:00",
      "close_time": "2025-11-28 14:35:00+00:00",
      "pnl": 0.0,
      "close_reason": "STOP_LOSS"
    },
    {
      "ticket": 101,
      "side": "SELL",
      "open_price": 0.5628724900527189,
      "close_price": 0.5714084999607189,
      "open_time": "2025-11-28 09:55:00+00:00",
      "close_time": "2025-11-28 15:30:00+00:00",
      "pnl": 0.0,
      "close_reason": "STOP_LOSS"
    },
    {
      "ticket": 104,
      "side": "BUY",
      "open_price": 0.5861430821958901,
      "close_price": 0.5780285776295969,
      "open_time": "2025-12-05 17:15:00+00:00",
      "close_time": "2025-12-05 17:40:00+00:00",
      "pnl": 0.0,
      "close_reason": "STOP_LOSS"
    },
    {
      "ticket": 105,
      "side": "BUY",
      "open_price": 0.5869531301179275,
      "close_price": 0.578090876472344,
      "open_time": "2025-12-05 17:25:00+00:00",
      "close_time": "2025-12-05 17:40:00+00:00",
      "pnl": 0.0,
      "close_reason": "STOP_LOSS"
    },
    {
      "ticket": 106,
      "side": "BUY",
      "open_price": 0.5857533539463257,
      "close_price": 0.5775992240657328,
      "open_time": "2025-12-05 17:50:00+00:00",
      "close_time": "2025-12-05 17:55:00+00:00",
      "pnl": 0.0,
      "close_reason": "STOP_LOSS"
    },
    {
      "ticket": 107,
      "side": "BUY",
      "open_price": 0.587923008614074,
      "close_price": 0.5792397156999534,
      "open_time": "2025-12-16 19:15:00+00:00",
      "close_time": "2025-12-16 19:40:00+00:00",
      "pnl": 0.0,
      "close_reason": "STOP_LOSS"
    },
    {
      "ticket": 108,
      "side": "SELL",
      "open_price": 0.5698605930768369,
      "close_price": 0.5776097911445831,
      "open_time": "2025-12-17 10:15:00+00:00",
      "close_time": "2025-12-17 10:25:00+00:00",
      "pnl": 0.0,
      "close_reason": "STOP_LOSS"
    },
    {
      "ticket": 109,
      "side": "SELL",
      "open_price": 0.5671438699876622,
      "close_price": 0.5760613761757857,
      "open_time": "2025-12-19 08:00:00+00:00",
      "close_time": "2025-12-19 08:05:00+00:00",
      "pnl": 0.0,
      "close_reason": "STOP_LOSS"
    },
    {
      "ticket": 110,
      "side": "SELL",
      "open_price": 0.5672900164138132,
      "close_price": 0.5747424662421856,
      "open_time": "2025-12-19 09:15:00+00:00",
      "close_time": "2025-12-19 09:40:00+00:00",
      "pnl": 0.0,
      "close_reason": "TAKE_PROFIT"
    },
    {
      "ticket": 111,
      "side": "SELL",
      "open_price": 0.5672312039505661,
      "close_price": 0.5737066055001597,
      "open_time": "2025-12-19 13:30:00+00:00",
      "close_time": "2025-12-19 15:10:00+00:00",
      "pnl": 0.0,
      "close_reason": "TAKE_PROFIT"
    },
    {
      "ticket": 112,
      "side": "SELL",
      "open_price": 0.5673456757205044,
      "close_price": 0.5744043357476045,
      "open_time": "2025-12-19 14:55:00+00:00",
      "close_time": "2025-12-19 15:30:00+00:00",
      "pnl": 0.0,
      "close_reason": "STOP_LOSS"
    },
    {
      "ticket": 113,
      "side": "BUY",
      "open_price": 0.5864959568089145,
      "close_price": 0.5781948827265035,
      "open_time": "2025-12-22 12:10:00+00:00",
      "close_time": "2025-12-22 12:30:00+00:00",
      "pnl": 0.0,
      "close_reason": "STOP_LOSS"
    },
    {
      "ticket": 114,
      "side": "BUY",
      "open_price": 0.5865079842821732,
      "close_price": 0.5784730665775272,
      "open_time": "2025-12-22 13:55:00+00:00",
      "close_time": "2025-12-22 14:20:00+00:00",
      "pnl": 0.0,
      "close_reason": "STOP_LOSS"
    },
    {
      "ticket": 115,
      "side": "BUY",
      "open_price": 0.5853495238362203,
      "close_price": 0.5786322229328139,
      "open_time": "2025-12-22 15:00:00+00:00",
      "close_time": "2025-12-22 16:00:00+00:00",
      "pnl": 0.0,
      "close_reason": "STOP_LOSS"
    },
    {
      "ticket": 117,
      "side": "BUY",
      "open_price": 0.5871495936282835,
      "close_price": 0.5795445056587718,
      "open_time": "2025-12-22 19:30:00+00:00",
      "close_time": "2025-12-22 20:05:00+00:00",
      "pnl": 0.0,
      "close_reason": "STOP_LOSS"
    },
    {
      "ticket": 116,
      "side": "BUY",
      "open_price": 0.5867290100682077,
      "close_price": 0.5788674804935161,
      "open_time": "2025-12-22 16:20:00+00:00",
      "close_time": "2025-12-23 00:00:00+00:00",
      "pnl": 0.0,
      "close_reason": "STOP_LOSS"
    },
    {
      "ticket": 118,
      "side": "BUY",
      "open_price": 0.5905234236982378,
      "close_price": 0.5835590354490873,
      "open_time": "2025-12-23 13:50:00+00:00",
      "close_time": "2025-12-23 15:30:00+00:00",
      "pnl": 0.0,
      "close_reason": "STOP_LOSS"
    },
    {
      "ticket": 119,
      "side": "BUY",
      "open_price": 0.5910393914466252,
      "close_price": 0.5830290701485267,
      "open_time": "2025-12-23 20:20:00+00:00",
      "close_time": "2025-12-24 00:00:00+00:00",
      "pnl": 0.0,
      "close_reason": "STOP_LOSS"
    },
    {
      "ticket": 121,
      "side": "SELL",
      "open_price": 0.5752196929685749,
      "close_price": 0.5833484950299268,
      "open_time": "2025-12-24 20:35:00+00:00",
      "close_time": "2025-12-24 20:40:00+00:00",
      "pnl": 0.0,
      "close_reason": "STOP_LOSS"
    },
    {
      "ticket": 122,
      "side": "SELL",
      "open_price": 0.5751764225071639,
      "close_price": 0.5836602656659775,
      "open_time": "2025-12-24 20:50:00+00:00",
      "close_time": "2025-12-26 00:00:00+00:00",
      "pnl": 0.0,
      "close_reason": "STOP_LOSS"
    },
    {
      "ticket": 120,
      "side": "SELL",
      "open_price": 0.5750935372721407,
      "close_price": 0.5841210777241463,
      "open_time": "2025-12-24 18:05:00+00:00",
      "close_time": "2025-12-26 03:35:00+00:00",
      "pnl": 0.0,
      "close_reason": "STOP_LOSS"
    },
    {
      "ticket": 124,
      "side": "SELL",
      "open_price": 0.5740109139180908,
      "close_price": 0.5819245024328622,
      "open_time": "2025-12-26 14:30:00+00:00",
      "close_time": "2025-12-26 14:35:00+00:00",
      "pnl": 0.0,
      "close_reason": "STOP_LOSS"
    },
    {
      "ticket": 123,
      "side": "SELL",
      "open_price": 0.5747900918385991,
      "close_price": 0.5822505699879956,
      "open_time": "2025-12-26 13:20:00+00:00",
      "close_time": "2025-12-26 15:00:00+00:00",
      "pnl": 0.0,
      "close_reason": "STOP_LOSS"
    },
    {
      "ticket": 125,
      "side": "SELL",
      "open_price": 0.5741074670672668,
      "close_price": 0.5819982527451086,
      "open_time": "2025-12-29 08:45:00+00:00",
      "close_time": "2025-12-29 09:20:00+00:00",
      "pnl": 0.0,
      "close_reason": "STOP_LOSS"
    },
    {
      "ticket": 126,
      "side": "SELL",
      "open_price": 0.5736589118210836,
      "close_price": 0.582309616472946,
      "open_time": "2025-12-29 09:20:00+00:00",
      "close_time": "2025-12-29 09:30:00+00:00",
      "pnl": 0.0,
      "close_reason": "STOP_LOSS"
    },
    {
      "ticket": 127,
      "side": "SELL",
      "open_price": 0.5730193115800329,
      "close_price": 0.5790455597911565,
      "open_time": "2025-12-29 13:00:00+00:00",
      "close_time": "2025-12-29 14:25:00+00:00",
      "pnl": 0.0,
      "close_reason": "TAKE_PROFIT"
    },
    {
      "ticket": 128,
      "side": "BUY",
      "open_price": 0.590393318244704,
      "close_price": 0.5814324550815537,
      "open_time": "2025-12-30 09:00:00+00:00",
      "close_time": "2025-12-30 09:05:00+00:00",
      "pnl": 0.0,
      "close_reason": "STOP_LOSS"
    },
    {
      "ticket": 129,
      "side": "SELL",
      "open_price": 0.5719614822428787,
      "close_price": 0.5812025835363285,
      "open_time": "2025-12-30 10:45:00+00:00",
      "close_time": "2025-12-30 11:00:00+00:00",
      "pnl": 0.0,
      "close_reason": "STOP_LOSS"
    },
    {
      "ticket": 130,
      "side": "SELL",
      "open_price": 0.5725009757974491,
      "close_price": 0.5802192654553272,
      "open_time": "2025-12-30 16:35:00+00:00",
      "close_time": "2025-12-30 17:00:00+00:00",
      "pnl": 0.0,
      "close_reason": "STOP_LOSS"
    },
    {
      "ticket": 131,
      "side": "SELL",
      "open_price": 0.5678916722486489,
      "close_price": 0.5764963364312928,
      "open_time": "2025-12-31 12:50:00+00:00",
      "close_time": "2025-12-31 13:05:00+00:00",
      "pnl": 0.0,
      "close_reason": "STOP_LOSS"
    },
    {
      "ticket": 132,
      "side": "SELL",
      "open_price": 0.5689646504453841,
      "close_price": 0.5743724818889142,
      "open_time": "2025-12-31 16:45:00+00:00",
      "close_time": "2025-12-31 17:45:00+00:00",
      "pnl": 0.0,
      "close_reason": "TAKE_PROFIT"
    },
    {
      "ticket": 133,
      "side": "SELL",
      "open_price": 0.5681002352452846,
      "close_price": 0.5760238426456855,
      "open_time": "2026-01-02 08:00:00+00:00",
      "close_time": "2026-01-02 09:20:00+00:00",
      "pnl": 0.0,
      "close_reason": "STOP_LOSS"
    },
    {
      "ticket": 134,
      "side": "BUY",
      "open_price": 0.5846145947882824,
      "close_price": 0.5769101034676432,
      "open_time": "2026-01-02 14:05:00+00:00",
      "close_time": "2026-01-02 14:10:00+00:00",
      "pnl": 0.0,
      "close_reason": "STOP_LOSS"
    },
    {
      "ticket": 135,
      "side": "SELL",
      "open_price": 0.5694783307865944,
      "close_price": 0.5767857219991164,
      "open_time": "2026-01-02 15:35:00+00:00",
      "close_time": "2026-01-02 16:20:00+00:00",
      "pnl": 0.0,
      "close_reason": "STOP_LOSS"
    },
    {
      "ticket": 136,
      "side": "BUY",
      "open_price": 0.5868129700040904,
      "close_price": 0.5787441546749056,
      "open_time": "2026-01-05 21:30:00+00:00",
      "close_time": "2026-01-05 23:40:00+00:00",
      "pnl": 0.0,
      "close_reason": "STOP_LOSS"
    },
    {
      "ticket": 137,
      "side": "BUY",
      "open_price": 0.5880518878304789,
      "close_price": 0.5798729149620793,
      "open_time": "2026-01-06 10:20:00+00:00",
      "close_time": "2026-01-06 10:30:00+00:00",
      "pnl": 0.0,
      "close_reason": "STOP_LOSS"
    },
    {
      "ticket": 138,
      "side": "SELL",
      "open_price": 0.5662889730554626,
      "close_price": 0.5752393985626628,
      "open_time": "2026-01-08 10:45:00+00:00",
      "close_time": "2026-01-08 17:15:00+00:00",
      "pnl": 0.0,
      "close_reason": "STOP_LOSS"
    },
    {
      "ticket": 139,
      "side": "SELL",
      "open_price": 0.5646390497104229,
      "close_price": 0.5727472945856092,
      "open_time": "2026-01-09 14:20:00+00:00",
      "close_time": "2026-01-09 15:30:00+00:00",
      "pnl": 0.0,
      "close_reason": "STOP_LOSS"
    },
    {
      "ticket": 141,
      "side": "BUY",
      "open_price": 0.5833012676777487,
      "close_price": 0.5752608215111993,
      "open_time": "2026-01-12 10:55:00+00:00",
      "close_time": "2026-01-12 11:00:00+00:00",
      "pnl": 0.0,
      "close_reason": "STOP_LOSS"
    },
    {
      "ticket": 142,
      "side": "BUY",
      "open_price": 0.5844118919514072,
      "close_price": 0.5753715862233808,
      "open_time": "2026-01-12 11:15:00+00:00",
      "close_time": "2026-01-12 11:45:00+00:00",
      "pnl": 0.0,
      "close_reason": "STOP_LOSS"
    },
    {
      "ticket": 140,
      "side": "BUY",
      "open_price": 0.5829242623110783,
      "close_price": 0.5762308341546332,
      "open_time": "2026-01-12 09:15:00+00:00",
      "close_time": "2026-01-12 14:40:00+00:00",
      "pnl": 0.0,
      "close_reason": "TAKE_PROFIT"
    },
    {
      "ticket": 143,
      "side": "SELL",
      "open_price": 0.5688085036777056,
      "close_price": 0.5767667479105377,
      "open_time": "2026-01-13 08:15:00+00:00",
      "close_time": "2026-01-13 10:25:00+00:00",
      "pnl": 0.0,
      "close_reason": "TAKE_PROFIT"
    },
    {
      "ticket": 144,
      "side": "SELL",
      "open_price": 0.5690655263455122,
      "close_price": 0.5770653508676299,
      "open_time": "2026-01-13 10:30:00+00:00",
      "close_time": "2026-01-13 11:00:00+00:00",
      "pnl": 0.0,
      "close_reason": "STOP_LOSS"
    },
    {
      "ticket": 145,
      "side": "SELL",
      "open_price": 0.5683209493526287,
      "close_price": 0.5757013100319781,
      "open_time": "2026-01-13 12:25:00+00:00",
      "close_time": "2026-01-13 15:00:00+00:00",
      "pnl": 0.0,
      "close_reason": "TAKE_PROFIT"
    },
    {
      "ticket": 146,
      "side": "BUY",
      "open_price": 0.5821326405485829,
      "close_price": 0.5744129188643942,
      "open_time": "2026-01-14 08:50:00+00:00",
      "close_time": "2026-01-14 10:05:00+00:00",
      "pnl": 0.0,
      "close_reason": "STOP_LOSS"
    },
    {
      "ticket": 147,
      "side": "BUY",
      "open_price": 0.5826950400962048,
      "close_price": 0.57502287913977,
      "open_time": "2026-01-14 18:20:00+00:00",
      "close_time": "2026-01-14 18:40:00+00:00",
      "pnl": 0.0,
      "close_reason": "STOP_LOSS"
    },
    {
      "ticket": 148,
      "side": "BUY",
      "open_price": 0.582507655255871,
      "close_price": 0.5746136699218685,
      "open_time": "2026-01-15 13:20:00+00:00",
      "close_time": "2026-01-15 13:45:00+00:00",
      "pnl": 0.0,
      "close_reason": "STOP_LOSS"
    },
    {
      "ticket": 149,
      "side": "BUY",
      "open_price": 0.5838663491538513,
      "close_price": 0.5757763241672123,
      "open_time": "2026-01-16 11:45:00+00:00",
      "close_time": "2026-01-16 12:00:00+00:00",
      "pnl": 0.0,
      "close_reason": "STOP_LOSS"
    },
    {
      "ticket": 150,
      "side": "BUY",
      "open_price": 0.5840559071564589,
      "close_price": 0.5757296377861031,
      "open_time": "2026-01-16 12:05:00+00:00",
      "close_time": "2026-01-16 12:10:00+00:00",
      "pnl": 0.0,
      "close_reason": "STOP_LOSS"
    },
    {
      "ticket": 151,
      "side": "BUY",
      "open_price": 0.5836113992571909,
      "close_price": 0.5759688046335102,
      "open_time": "2026-01-16 12:40:00+00:00",
      "close_time": "2026-01-16 12:55:00+00:00",
      "pnl": 0.0,
      "close_reason": "STOP_LOSS"
    },
    {
      "ticket": 152,
      "side": "SELL",
      "open_price": 0.567918006778884,
      "close_price": 0.5746456294411275,
      "open_time": "2026-01-16 17:10:00+00:00",
      "close_time": "2026-01-16 17:40:00+00:00",
      "pnl": 0.0,
      "close_reason": "TAKE_PROFIT"
    },
    {
      "ticket": 153,
      "side": "SELL",
      "open_price": 0.5661533461440319,
      "close_price": 0.5753555352352064,
      "open_time": "2026-01-16 17:35:00+00:00",
      "close_time": "2026-01-19 01:05:00+00:00",
      "pnl": 0.0,
      "close_reason": "STOP_LOSS"
    },
    {
      "ticket": 154,
      "side": "BUY",
      "open_price": 0.5855575191708633,
      "close_price": 0.5772802974849518,
      "open_time": "2026-01-19 08:00:00+00:00",
      "close_time": "2026-01-19 08:15:00+00:00",
      "pnl": 0.0,
      "close_reason": "STOP_LOSS"
    },
    {
      "ticket": 155,
      "side": "BUY",
      "open_price": 0.5850080909497051,
      "close_price": 0.5784480562543131,
      "open_time": "2026-01-19 12:00:00+00:00",
      "close_time": "2026-01-19 12:50:00+00:00",
      "pnl": 0.0,
      "close_reason": "TAKE_PROFIT"
    },
    {
      "ticket": 156,
      "side": "BUY",
      "open_price": 0.5868915997110914,
      "close_price": 0.579388115070927,
      "open_time": "2026-01-19 20:30:00+00:00",
      "close_time": "2026-01-19 20:45:00+00:00",
      "pnl": 0.0,
      "close_reason": "STOP_LOSS"
    },
    {
      "ticket": 157,
      "side": "BUY",
      "open_price": 0.5918314009145231,
      "close_price": 0.5836456664456032,
      "open_time": "2026-01-20 13:50:00+00:00",
      "close_time": "2026-01-20 14:30:00+00:00",
      "pnl": 0.0,
      "close_reason": "STOP_LOSS"
    },
    {
      "ticket": 158,
      "side": "BUY",
      "open_price": 0.5920249023799957,
      "close_price": 0.5836042203318451,
      "open_time": "2026-01-20 17:20:00+00:00",
      "close_time": "2026-01-20 20:35:00+00:00",
      "pnl": 0.0,
      "close_reason": "STOP_LOSS"
    },
    {
      "ticket": 159,
      "side": "BUY",
      "open_price": 0.5932142097468082,
      "close_price": 0.5842621791969179,
      "open_time": "2026-01-21 11:40:00+00:00",
      "close_time": "2026-01-21 11:45:00+00:00",
      "pnl": 0.0,
      "close_reason": "STOP_LOSS"
    },
    {
      "ticket": 160,
      "side": "BUY",
      "open_price": 0.5925099972739094,
      "close_price": 0.5852994810883578,
      "open_time": "2026-01-21 16:20:00+00:00",
      "close_time": "2026-01-21 17:15:00+00:00",
      "pnl": 0.0,
      "close_reason": "STOP_LOSS"
    },
    {
      "ticket": 161,
      "side": "SELL",
      "open_price": 0.5760340758558097,
      "close_price": 0.5846948058778701,
      "open_time": "2026-01-21 19:30:00+00:00",
      "close_time": "2026-01-21 21:55:00+00:00",
      "pnl": 0.0,
      "close_reason": "STOP_LOSS"
    },
    {
      "ticket": 162,
      "side": "BUY",
      "open_price": 0.5933195962672376,
      "close_price": 0.5853782943441677,
      "open_time": "2026-01-22 08:00:00+00:00",
      "close_time": "2026-01-22 08:05:00+00:00",
      "pnl": 0.0,
      "close_reason": "STOP_LOSS"
    },
    {
      "ticket": 163,
      "side": "BUY",
      "open_price": 0.5950184107936087,
      "close_price": 0.5874414463385406,
      "open_time": "2026-01-22 11:00:00+00:00",
      "close_time": "2026-01-22 12:55:00+00:00",
      "pnl": 0.0,
      "close_reason": "TAKE_PROFIT"
    },
    {
      "ticket": 164,
      "side": "SELL",
      "open_price": 0.5829980717079294,
      "close_price": 0.590842284312822,
      "open_time": "2026-01-23 09:20:00+00:00",
      "close_time": "2026-01-23 09:40:00+00:00",
      "pnl": 0.0,
      "close_reason": "STOP_LOSS"
    },
    {
      "ticket": 165,
      "side": "SELL",
      "open_price": 0.5870937132433722,
      "close_price": 0.5958127387732887,
      "open_time": "2026-01-26 09:00:00+00:00",
      "close_time": "2026-01-26 09:05:00+00:00",
      "pnl": 0.0,
      "close_reason": "STOP_LOSS"
    },
    {
      "ticket": 166,
      "side": "BUY",
      "open_price": 0.6163295529948004,
      "close_price": 0.6077268140657451,
      "open_time": "2026-01-29 09:20:00+00:00",
      "close_time": "2026-01-29 09:25:00+00:00",
      "pnl": 0.0,
      "close_reason": "STOP_LOSS"
    },
    {
      "ticket": 167,
      "side": "BUY",
      "open_price": 0.6114309276846785,
      "close_price": 0.6053814903263476,
      "open_time": "2026-02-03 08:20:00+00:00",
      "close_time": "2026-02-03 09:40:00+00:00",
      "pnl": 0.0,
      "close_reason": "TAKE_PROFIT"
    },
    {
      "ticket": 169,
      "side": "SELL",
      "open_price": 0.5912629098001558,
      "close_price": 0.5996836054701834,
      "open_time": "2026-02-04 21:20:00+00:00",
      "close_time": "2026-02-04 21:30:00+00:00",
      "pnl": 0.0,
      "close_reason": "STOP_LOSS"
    },
    {
      "ticket": 170,
      "side": "SELL",
      "open_price": 0.5922612446194837,
      "close_price": 0.6002666704308219,
      "open_time": "2026-02-04 21:30:00+00:00",
      "close_time": "2026-02-04 21:45:00+00:00",
      "pnl": 0.0,
      "close_reason": "STOP_LOSS"
    },
    {
      "ticket": 168,
      "side": "SELL",
      "open_price": 0.5932738399992472,
      "close_price": 0.5981938970018954,
      "open_time": "2026-02-04 17:40:00+00:00",
      "close_time": "2026-02-05 04:15:00+00:00",
      "pnl": 0.0,
      "close_reason": "TAKE_PROFIT"
    },
    {
      "ticket": 171,
      "side": "BUY",
      "open_price": 0.6066227200709613,
      "close_price": 0.5987187865627086,
      "open_time": "2026-02-05 09:30:00+00:00",
      "close_time": "2026-02-05 09:40:00+00:00",
      "pnl": 0.0,
      "close_reason": "STOP_LOSS"
    },
    {
      "ticket": 172,
      "side": "BUY",
      "open_price": 0.6068745544577838,
      "close_price": 0.5997045815898918,
      "open_time": "2026-02-06 11:25:00+00:00",
      "close_time": "2026-02-06 15:20:00+00:00",
      "pnl": 0.0,
      "close_reason": "TAKE_PROFIT"
    },
    {
      "ticket": 173,
      "side": "BUY",
      "open_price": 0.6128623949680749,
      "close_price": 0.6046311633970246,
      "open_time": "2026-02-09 19:55:00+00:00",
      "close_time": "2026-02-09 20:20:00+00:00",
      "pnl": 0.0,
      "close_reason": "STOP_LOSS"
    },
    {
      "ticket": 174,
      "side": "SELL",
      "open_price": 0.5946972424258281,
      "close_price": 0.603762241878323,
      "open_time": "2026-02-10 08:15:00+00:00",
      "close_time": "2026-02-10 09:05:00+00:00",
      "pnl": 0.0,
      "close_reason": "STOP_LOSS"
    },
    {
      "ticket": 175,
      "side": "BUY",
      "open_price": 0.613087485583365,
      "close_price": 0.6039447901681649,
      "open_time": "2026-02-10 10:40:00+00:00",
      "close_time": "2026-02-10 12:25:00+00:00",
      "pnl": 0.0,
      "close_reason": "STOP_LOSS"
    },
    {
      "ticket": 176,
      "side": "BUY",
      "open_price": 0.6148591438781376,
      "close_price": 0.6062138186964312,
      "open_time": "2026-02-11 12:30:00+00:00",
      "close_time": "2026-02-11 13:40:00+00:00",
      "pnl": 0.0,
      "close_reason": "STOP_LOSS"
    },
    {
      "ticket": 177,
      "side": "SELL",
      "open_price": 0.596229452279843,
      "close_price": 0.6057179536560637,
      "open_time": "2026-02-11 15:30:00+00:00",
      "close_time": "2026-02-11 15:45:00+00:00",
      "pnl": 0.0,
      "close_reason": "STOP_LOSS"
    },
    {
      "ticket": 178,
      "side": "SELL",
      "open_price": 0.595408687968859,
      "close_price": 0.6053810016845728,
      "open_time": "2026-02-11 17:15:00+00:00",
      "close_time": "2026-02-11 18:35:00+00:00",
      "pnl": 0.0,
      "close_reason": "STOP_LOSS"
    },
    {
      "ticket": 179,
      "side": "BUY",
      "open_price": 0.6140185371478748,
      "close_price": 0.6058782985084797,
      "open_time": "2026-02-11 21:15:00+00:00",
      "close_time": "2026-02-11 21:25:00+00:00",
      "pnl": 0.0,
      "close_reason": "STOP_LOSS"
    },
    {
      "ticket": 180,
      "side": "BUY",
      "open_price": 0.6132200901423339,
      "close_price": 0.6054471821470355,
      "open_time": "2026-02-11 21:55:00+00:00",
      "close_time": "2026-02-11 22:00:00+00:00",
      "pnl": 0.0,
      "close_reason": "STOP_LOSS"
    },
    {
      "ticket": 181,
      "side": "SELL",
      "open_price": 0.596120445275559,
      "close_price": 0.6045508243097599,
      "open_time": "2026-02-12 08:30:00+00:00",
      "close_time": "2026-02-12 08:40:00+00:00",
      "pnl": 0.0,
      "close_reason": "STOP_LOSS"
    },
    {
      "ticket": 182,
      "side": "SELL",
      "open_price": 0.5969794210335214,
      "close_price": 0.6039134561285969,
      "open_time": "2026-02-13 15:30:00+00:00",
      "close_time": "2026-02-13 15:35:00+00:00",
      "pnl": 0.0,
      "close_reason": "STOP_LOSS"
    },
    {
      "ticket": 183,
      "side": "SELL",
      "open_price": 0.594577130445756,
      "close_price": 0.6033579824182049,
      "open_time": "2026-02-16 20:40:00+00:00",
      "close_time": "2026-02-16 20:50:00+00:00",
      "pnl": 0.0,
      "close_reason": "STOP_LOSS"
    },
    {
      "ticket": 184,
      "side": "BUY",
      "open_price": 0.6119098566236066,
      "close_price": 0.6031060560604773,
      "open_time": "2026-02-17 08:00:00+00:00",
      "close_time": "2026-02-17 09:05:00+00:00",
      "pnl": 0.0,
      "close_reason": "STOP_LOSS"
    },
    {
      "ticket": 185,
      "side": "SELL",
      "open_price": 0.5925585168131546,
      "close_price": 0.6022211865615469,
      "open_time": "2026-02-17 17:05:00+00:00",
      "close_time": "2026-02-17 18:10:00+00:00",
      "pnl": 0.0,
      "close_reason": "STOP_LOSS"
    },
    {
      "ticket": 186,
      "side": "BUY",
      "open_price": 0.6118325957231819,
      "close_price": 0.6048109797549324,
      "open_time": "2026-02-17 20:10:00+00:00",
      "close_time": "2026-02-17 20:40:00+00:00",
      "pnl": 0.0,
      "close_reason": "TAKE_PROFIT"
    },
    {
      "ticket": 187,
      "side": "SELL",
      "open_price": 0.5917978930077735,
      "close_price": 0.5997742144828958,
      "open_time": "2026-02-18 08:15:00+00:00",
      "close_time": "2026-02-18 08:30:00+00:00",
      "pnl": 0.0,
      "close_reason": "STOP_LOSS"
    },
    {
      "ticket": 188,
      "side": "SELL",
      "open_price": 0.5917503810453175,
      "close_price": 0.5999121081193556,
      "open_time": "2026-02-18 08:35:00+00:00",
      "close_time": "2026-02-18 08:45:00+00:00",
      "pnl": 0.0,
      "close_reason": "STOP_LOSS"
    },
    {
      "ticket": 189,
      "side": "SELL",
      "open_price": 0.5910529119794738,
      "close_price": 0.5969769474305817,
      "open_time": "2026-02-18 18:50:00+00:00",
      "close_time": "2026-02-18 21:00:00+00:00",
      "pnl": 0.0,
      "close_reason": "TAKE_PROFIT"
    },
    {
      "ticket": 190,
      "side": "SELL",
      "open_price": 0.5903848623736986,
      "close_price": 0.5966644962851614,
      "open_time": "2026-02-18 20:05:00+00:00",
      "close_time": "2026-02-18 21:15:00+00:00",
      "pnl": 0.0,
      "close_reason": "TAKE_PROFIT"
    },
    {
      "ticket": 191,
      "side": "SELL",
      "open_price": 0.5904803315144881,
      "close_price": 0.5964963919906326,
      "open_time": "2026-02-18 20:15:00+00:00",
      "close_time": "2026-02-18 21:30:00+00:00",
      "pnl": 0.0,
      "close_reason": "TAKE_PROFIT"
    },
    {
      "ticket": 192,
      "side": "SELL",
      "open_price": 0.5867727472235509,
      "close_price": 0.594907755566787,
      "open_time": "2026-02-24 16:10:00+00:00",
      "close_time": "2026-02-24 16:35:00+00:00",
      "pnl": 0.0,
      "close_reason": "STOP_LOSS"
    },
    {
      "ticket": 193,
      "side": "BUY",
      "open_price": 0.6065802397482633,
      "close_price": 0.5980672318221848,
      "open_time": "2026-02-25 08:00:00+00:00",
      "close_time": "2026-02-25 08:05:00+00:00",
      "pnl": 0.0,
      "close_reason": "STOP_LOSS"
    },
    {
      "ticket": 194,
      "side": "BUY",
      "open_price": 0.6086672779690374,
      "close_price": 0.6005027020778041,
      "open_time": "2026-02-26 08:00:00+00:00",
      "close_time": "2026-02-26 08:15:00+00:00",
      "pnl": 0.0,
      "close_reason": "STOP_LOSS"
    },
    {
      "ticket": 195,
      "side": "SELL",
      "open_price": 0.589744807221052,
      "close_price": 0.5986545219749897,
      "open_time": "2026-02-26 12:45:00+00:00",
      "close_time": "2026-02-26 13:00:00+00:00",
      "pnl": 0.0,
      "close_reason": "STOP_LOSS"
    },
    {
      "ticket": 196,
      "side": "SELL",
      "open_price": 0.5916601286602202,
      "close_price": 0.5988755660154597,
      "open_time": "2026-02-26 13:05:00+00:00",
      "close_time": "2026-02-26 13:10:00+00:00",
      "pnl": 0.0,
      "close_reason": "STOP_LOSS"
    },
    {
      "ticket": 197,
      "side": "SELL",
      "open_price": 0.590778244385633,
      "close_price": 0.5983032230844255,
      "open_time": "2026-02-27 14:45:00+00:00",
      "close_time": "2026-02-27 15:20:00+00:00",
      "pnl": 0.0,
      "close_reason": "STOP_LOSS"
    },
    {
      "ticket": 198,
      "side": "SELL",
      "open_price": 0.5902496733312029,
      "close_price": 0.5981170963678248,
      "open_time": "2026-02-27 15:35:00+00:00",
      "close_time": "2026-02-27 16:10:00+00:00",
      "pnl": 0.0,
      "close_reason": "STOP_LOSS"
    },
    {
      "ticket": 199,
      "side": "SELL",
      "open_price": 0.587734313576786,
      "close_price": 0.5942675116738247,
      "open_time": "2026-03-02 08:00:00+00:00",
      "close_time": "2026-03-02 09:15:00+00:00",
      "pnl": 0.0,
      "close_reason": "TAKE_PROFIT"
    },
    {
      "ticket": 200,
      "side": "BUY",
      "open_price": 0.5974688926516273,
      "close_price": 0.5879514547707682,
      "open_time": "2026-03-03 20:20:00+00:00",
      "close_time": "2026-03-04 00:20:00+00:00",
      "pnl": 0.0,
      "close_reason": "STOP_LOSS"
    },
    {
      "ticket": 201,
      "side": "BUY",
      "open_price": 0.5990385195522777,
      "close_price": 0.5915242746814293,
      "open_time": "2026-03-04 14:10:00+00:00",
      "close_time": "2026-03-04 14:15:00+00:00",
      "pnl": 0.0,
      "close_reason": "STOP_LOSS"
    },
    {
      "ticket": 202,
      "side": "BUY",
      "open_price": 0.5984781866637775,
      "close_price": 0.5905356185668975,
      "open_time": "2026-03-04 14:25:00+00:00",
      "close_time": "2026-03-04 14:30:00+00:00",
      "pnl": 0.0,
      "close_reason": "STOP_LOSS"
    },
    {
      "ticket": 203,
      "side": "BUY",
      "open_price": 0.6010968993354622,
      "close_price": 0.593003691011954,
      "open_time": "2026-03-04 20:50:00+00:00",
      "close_time": "2026-03-05 00:00:00+00:00",
      "pnl": 0.0,
      "close_reason": "STOP_LOSS"
    },
    {
      "ticket": 205,
      "side": "SELL",
      "open_price": 0.5789769048948147,
      "close_price": 0.588007348960558,
      "open_time": "2026-03-05 21:35:00+00:00",
      "close_time": "2026-03-05 21:50:00+00:00",
      "pnl": 0.0,
      "close_reason": "STOP_LOSS"
    },
    {
      "ticket": 204,
      "side": "SELL",
      "open_price": 0.5808611285576492,
      "close_price": 0.5884678589700497,
      "open_time": "2026-03-05 20:55:00+00:00",
      "close_time": "2026-03-05 22:05:00+00:00",
      "pnl": 0.0,
      "close_reason": "STOP_LOSS"
    },
    {
      "ticket": 206,
      "side": "BUY",
      "open_price": 0.5982852491736627,
      "close_price": 0.5891200587161162,
      "open_time": "2026-03-06 19:40:00+00:00",
      "close_time": "2026-03-09 00:00:00+00:00",
      "pnl": 0.0,
      "close_reason": "STOP_LOSS"
    },
    {
      "ticket": 208,
      "side": "BUY",
      "open_price": 0.5965440596977314,
      "close_price": 0.5885382714137368,
      "open_time": "2026-03-09 10:50:00+00:00",
      "close_time": "2026-03-09 11:15:00+00:00",
      "pnl": 0.0,
      "close_reason": "STOP_LOSS"
    },
    {
      "ticket": 207,
      "side": "BUY",
      "open_price": 0.5958661149531613,
      "close_price": 0.5900300248723906,
      "open_time": "2026-03-09 08:05:00+00:00",
      "close_time": "2026-03-09 12:20:00+00:00",
      "pnl": 0.0,
      "close_reason": "TAKE_PROFIT"
    },
    {
      "ticket": 209,
      "side": "BUY",
      "open_price": 0.5972561305385558,
      "close_price": 0.5898106792765252,
      "open_time": "2026-03-09 15:45:00+00:00",
      "close_time": "2026-03-09 15:50:00+00:00",
      "pnl": 0.0,
      "close_reason": "STOP_LOSS"
    },
    {
      "ticket": 210,
      "side": "BUY",
      "open_price": 0.599878043066607,
      "close_price": 0.5915824402229897,
      "open_time": "2026-03-09 19:10:00+00:00",
      "close_time": "2026-03-09 19:15:00+00:00",
      "pnl": 0.0,
      "close_reason": "STOP_LOSS"
    },
    {
      "ticket": 211,
      "side": "BUY",
      "open_price": 0.6016641527030475,
      "close_price": 0.5932565272447721,
      "open_time": "2026-03-10 12:40:00+00:00",
      "close_time": "2026-03-10 13:00:00+00:00",
      "pnl": 0.0,
      "close_reason": "STOP_LOSS"
    },
    {
      "ticket": 212,
      "side": "SELL",
      "open_price": 0.5857508858610122,
      "close_price": 0.5921280051180152,
      "open_time": "2026-03-11 10:25:00+00:00",
      "close_time": "2026-03-11 11:50:00+00:00",
      "pnl": 0.0,
      "close_reason": "TAKE_PROFIT"
    },
    {
      "ticket": 213,
      "side": "SELL",
      "open_price": 0.5771675733568715,
      "close_price": 0.5862293644296951,
      "open_time": "2026-03-12 20:10:00+00:00",
      "close_time": "2026-03-12 20:20:00+00:00",
      "pnl": 0.0,
      "close_reason": "STOP_LOSS"
    },
    {
      "ticket": 214,
      "side": "SELL",
      "open_price": 0.577886319165528,
      "close_price": 0.5857232044834342,
      "open_time": "2026-03-12 21:35:00+00:00",
      "close_time": "2026-03-12 22:35:00+00:00",
      "pnl": 0.0,
      "close_reason": "STOP_LOSS"
    },
    {
      "ticket": 216,
      "side": "BUY",
      "open_price": 0.5909548486487538,
      "close_price": 0.582932464060832,
      "open_time": "2026-03-13 15:55:00+00:00",
      "close_time": "2026-03-13 16:00:00+00:00",
      "pnl": 0.0,
      "close_reason": "STOP_LOSS"
    },
    {
      "ticket": 217,
      "side": "BUY",
      "open_price": 0.5901908731417563,
      "close_price": 0.5832053002985432,
      "open_time": "2026-03-13 16:55:00+00:00",
      "close_time": "2026-03-13 17:00:00+00:00",
      "pnl": 0.0,
      "close_reason": "STOP_LOSS"
    },
    {
      "ticket": 218,
      "side": "BUY",
      "open_price": 0.5916030407196085,
      "close_price": 0.5828474134114398,
      "open_time": "2026-03-13 17:15:00+00:00",
      "close_time": "2026-03-13 17:40:00+00:00",
      "pnl": 0.0,
      "close_reason": "STOP_LOSS"
    },
    {
      "ticket": 215,
      "side": "BUY",
      "open_price": 0.5905745216305756,
      "close_price": 0.5823068780384628,
      "open_time": "2026-03-13 14:40:00+00:00",
      "close_time": "2026-03-13 17:45:00+00:00",
      "pnl": 0.0,
      "close_reason": "STOP_LOSS"
    },
    {
      "ticket": 219,
      "side": "BUY",
      "open_price": 0.5903316156414586,
      "close_price": 0.5822680260953292,
      "open_time": "2026-03-13 17:40:00+00:00",
      "close_time": "2026-03-13 17:45:00+00:00",
      "pnl": 0.0,
      "close_reason": "STOP_LOSS"
    },
    {
      "ticket": 220,
      "side": "BUY",
      "open_price": 0.5908248157813841,
      "close_price": 0.5856930347328705,
      "open_time": "2026-03-16 16:25:00+00:00",
      "close_time": "2026-03-16 16:55:00+00:00",
      "pnl": 0.0,
      "close_reason": "TAKE_PROFIT"
    },
    {
      "ticket": 221,
      "side": "BUY",
      "open_price": 0.5918831628231142,
      "close_price": 0.5843602926179693,
      "open_time": "2026-03-16 16:40:00+00:00",
      "close_time": "2026-03-16 17:45:00+00:00",
      "pnl": 0.0,
      "close_reason": "STOP_LOSS"
    },
    {
      "ticket": 222,
      "side": "SELL",
      "open_price": 0.5755459316213929,
      "close_price": 0.5834721689713713,
      "open_time": "2026-03-17 11:40:00+00:00",
      "close_time": "2026-03-17 11:50:00+00:00",
      "pnl": 0.0,
      "close_reason": "STOP_LOSS"
    },
    {
      "ticket": 223,
      "side": "BUY",
      "open_price": 0.5953482100776611,
      "close_price": 0.5861297995438357,
      "open_time": "2026-03-17 21:00:00+00:00",
      "close_time": "2026-03-17 21:35:00+00:00",
      "pnl": 0.0,
      "close_reason": "STOP_LOSS"
    },
    {
      "ticket": 224,
      "side": "BUY",
      "open_price": 0.5939753318235129,
      "close_price": 0.5881199451798108,
      "open_time": "2026-03-19 21:55:00+00:00",
      "close_time": "2026-03-19 22:05:00+00:00",
      "pnl": 0.0,
      "close_reason": "TAKE_PROFIT"
    },
    {
      "ticket": 225,
      "side": "SELL",
      "open_price": 0.5792155657512716,
      "close_price": 0.5880504429495749,
      "open_time": "2026-03-20 08:50:00+00:00",
      "close_time": "2026-03-20 09:05:00+00:00",
      "pnl": 0.0,
      "close_reason": "STOP_LOSS"
    },
    {
      "ticket": 226,
      "side": "SELL",
      "open_price": 0.5806920464930825,
      "close_price": 0.5882321721967946,
      "open_time": "2026-03-20 10:10:00+00:00",
      "close_time": "2026-03-20 10:15:00+00:00",
      "pnl": 0.0,
      "close_reason": "STOP_LOSS"
    },
    {
      "ticket": 227,
      "side": "SELL",
      "open_price": 0.5718272953819883,
      "close_price": 0.5793294145018114,
      "open_time": "2026-03-23 08:20:00+00:00",
      "close_time": "2026-03-23 09:10:00+00:00",
      "pnl": 0.0,
      "close_reason": "TAKE_PROFIT"
    },
    {
      "ticket": 228,
      "side": "SELL",
      "open_price": 0.5724496029922266,
      "close_price": 0.5784582546547303,
      "open_time": "2026-03-23 11:30:00+00:00",
      "close_time": "2026-03-23 12:30:00+00:00",
      "pnl": 0.0,
      "close_reason": "TAKE_PROFIT"
    },
    {
      "ticket": 229,
      "side": "SELL",
      "open_price": 0.5744300506201641,
      "close_price": 0.5829254432376119,
      "open_time": "2026-03-24 08:50:00+00:00",
      "close_time": "2026-03-24 08:55:00+00:00",
      "pnl": 0.0,
      "close_reason": "STOP_LOSS"
    },
    {
      "ticket": 230,
      "side": "BUY",
      "open_price": 0.5906604201001916,
      "close_price": 0.5815295767765878,
      "open_time": "2026-03-25 11:15:00+00:00",
      "close_time": "2026-03-25 12:35:00+00:00",
      "pnl": 0.0,
      "close_reason": "STOP_LOSS"
    },
    {
      "ticket": 231,
      "side": "SELL",
      "open_price": 0.5728688337083473,
      "close_price": 0.5815381232988458,
      "open_time": "2026-03-25 18:55:00+00:00",
      "close_time": "2026-03-25 19:00:00+00:00",
      "pnl": 0.0,
      "close_reason": "STOP_LOSS"
    },
    {
      "ticket": 232,
      "side": "SELL",
      "open_price": 0.5712366119716268,
      "close_price": 0.5776987655327134,
      "open_time": "2026-03-26 13:10:00+00:00",
      "close_time": "2026-03-26 14:40:00+00:00",
      "pnl": 0.0,
      "close_reason": "TAKE_PROFIT"
    }
  ]
}